Workbook

Sheet Data
A2: Year | B2: JUL | C2: PO No. | D2: Supplier Name. | E2: Description of Goods/Service | F2: Qty | G2: Unit | H2: ราคาต่ำสุดต่อหน่วย | I2: ราคารวม | J2: ราคาที่ต่อรองได้ | K2: ผลต่าง | L2: รวมที่ต่อรองได้ | M2: % discount | N2: Method for discounts | O2: Person in charge
A3: 2023 | B3: JAN | C3: PO-23000001 | D3: บริษัท เอทีซี อินดัสตรี (ประเทศไทย)จำกัด | E3: ทินเนอร์ THINNER AAA | F3: 36 | G3: EA | H3: 460 | I3: =H3*F3 -> 16560 | J3: 420 | K3: =H3-J3 -> 40 | L3: =K3*F3 -> 1440 | M3: =K3/H3 -> 0.086956522 | N3: Avoidance | O3: Saniya | P3: Compare + Negotiate
A4: 2023 | B4: JAN | C4: PO-23000002 | D4: บริษัท เอ็นทีดับเบิ้ลยู เอ็นจิเนียริ่ง ซัพพลาย จำกัด | E4: สีสเปรย์ KOBE สีดำด้าน เบอร์ 912 | F4: 36 | G4: EA | H4: 44.5 | I4: =H4*F4 -> 1602 | J4: 39 | K4: =H4-J4 -> 5.5 | L4: =K4*F4 -> 198 | M4: =K4/H4 -> 0.12359551 | N4: Compare + Negotiate | O4: Saniya | P4: Avoidance
A5: 2023 | B5: JAN | C5: PO-23000016 | D5: บริษัท บ้านไฟฟ้า จำกัด | E5: สายไฟ H07V-K 1*1.5 SQ.MM. GNYE (สีเขียวแถบเหลือง) | F5: 2 | G5: Roll | H5: 1200 | I5: =H5*F5 -> 2400 | J5: 990 | K5: =H5-J5 -> 210 | L5: =K5*F5 -> 420 | M5: =K5/H5 -> 0.175 | N5: Compare + Negotiate | O5: Saniya | P5: เพิ่มเครดิต
A6: 2023 | B6: JAN | C6: PO-23000077 | D6: บริษัท เอทีซี อินดัสตรี (ประเทศไทย)จำกัด | E6: สก๊อตเทปใส Unitape size 1/2" IN x 72 YDS | F6: 576 | G6: Roll | H6: 28 | I6: =H6*F6 -> 16128 | J6: 25 | K6: =H6-J6 -> 3 | L6: =K6*F6 -> 1728 | M6: =K6/H6 -> 0.10714286 | N6: Avoidance | O6: Saniya | P6: Rebate
A7: 2023 | B7: JAN | C7: PO-23000087 | D7: ห้างหุ้นส่วนจำกัด บางกอกคอปเปอร์ | E7: ลวดแบนหุ้มกระดาษหนา 0.5 มม. ขนาด 3.0*13 มม. | F7: 1893 | G7: KG | H7: 360 | I7: =H7*F7 -> 681480 | J7: 359.5 | K7: =H7-J7 -> 0.5 | L7: =K7*F7 -> 946.5 | M7: =K7/H7 -> 0.0013888889 | N7: Negotiate | O7: Pawina | P7: Negotiate
A8: 2023 | B8: JAN | C8: PO-23000087 | D8: ห้างหุ้นส่วนจำกัด บางกอกคอปเปอร์ | E8: ลวดแบนหุ้มกระดาษหนา 0.5 มม. ขนาด 3.0*13 มม. | F8: 1893 | G8: KG | H8: 360 | I8: =H8*F8 -> 681480 | J8: 359.5 | K8: =H8-J8 -> 0.5 | L8: =K8*F8 -> 946.5 | M8: =K8/H8 -> 0.0013888889 | N8: Negotiate | O8: Pawina
A9: 2023 | B9: JAN | C9: PO-23000087 | D9: ห้างหุ้นส่วนจำกัด บางกอกคอปเปอร์ | E9: ลวดแบนหุ้มกระดาษหนา 0.5 มม. ขนาด 2.8*11 มม. | F9: 110 | G9: KG | H9: 360 | I9: =H9*F9 -> 39600 | J9: 359.5 | K9: =H9-J9 -> 0.5 | L9: =K9*F9 -> 55 | M9: =K9/H9 -> 0.0013888889 | N9: Negotiate | O9: Pawina
A10: 2023 | B10: JAN | C10: PO-23000087 | D10: ห้างหุ้นส่วนจำกัด บางกอกคอปเปอร์ | E10: ลวดแบนหุ้มกระดาษหนา 0.5 มม. ขนาด 1.8 *4.0 มม. | F10: 321 | G10: KG | H10: 360 | I10: =H10*F10 -> 115560 | J10: 359.5 | K10: =H10-J10 -> 0.5 | L10: =K10*F10 -> 160.5 | M10: =K10/H10 -> 0.0013888889 | N10: Negotiate | O10: Pawina
A11: 2023 | B11: JAN | C11: PO-23000014 | D11: บริษัท ตงเฉินอีเล็คทริคเคเบิ้ลแอนด์ ไวร์ จำกัด | E11: ลวดกลมอาบน้ำยา ขนาด 1.50 มม. | F11: 593.27 | G11: KG | H11: 346 | I11: =H11*F11 -> 205271.42 | J11: 334 | K11: =H11-J11 -> 12 | L11: =K11*F11 -> 7119.24 | M11: =K11/H11 -> 0.034682081 | N11: Negotiate | O11: Pawina
A12: 2023 | B12: JAN | C12: PO-23000014 | D12: บริษัท ตงเฉินอีเล็คทริคเคเบิ้ลแอนด์ ไวร์ จำกัด | E12: ลวดกลมอาบน้ำยา ขนาด 1.40 มม. | F12: 295.02 | G12: KG | H12: 346 | I12: =H12*F12 -> 102076.92 | J12: 334.5 | K12: =H12-J12 -> 11.5 | L12: =K12*F12 -> 3392.73 | M12: =K12/H12 -> 0.033236994 | N12: Negotiate | O12: Pawina
A13: 2023 | B13: JAN | C13: PO-23000014 | D13: บริษัท ตงเฉินอีเล็คทริคเคเบิ้ลแอนด์ ไวร์ จำกัด | E13: ลวดกลมอาบน้ำยา ขนาด 1.50 มม. | F13: 688.13 | G13: KG | H13: 346 | I13: =H13*F13 -> 238092.98 | J13: 334 | K13: =H13-J13 -> 12 | L13: =K13*F13 -> 8257.56 | M13: =K13/H13 -> 0.034682081 | N13: Negotiate | O13: Pawina
A14: 2023 | B14: JAN | C14: PO-23000014 | D14: บริษัท ตงเฉินอีเล็คทริคเคเบิ้ลแอนด์ ไวร์ จำกัด | E14: ลวดกลมอาบน้ำยา ขนาด 0.95 มม. | F14: 607.18 | G14: KG | H14: 349 | I14: =H14*F14 -> 211905.82 | J14: 338.5 | K14: =H14-J14 -> 10.5 | L14: =K14*F14 -> 6375.39 | M14: =K14/H14 -> 0.03008596 | N14: Negotiate | O14: Pawina
A15: 2023 | B15: JAN | C15: PO-23000014 | D15: บริษัท ตงเฉินอีเล็คทริคเคเบิ้ลแอนด์ ไวร์ จำกัด | E15: ลวดกลมอาบน้ำยา ขนาด 0.75 มม. | F15: 101.67 | G15: KG | H15: 350 | I15: =H15*F15 -> 35584.5 | J15: 340 | K15: =H15-J15 -> 10 | L15: =K15*F15 -> 1016.7 | M15: =K15/H15 -> 0.028571429 | N15: Negotiate | O15: Pawina
A16: 2023 | B16: JAN | C16: PO-23000014 | D16: บริษัท ตงเฉินอีเล็คทริคเคเบิ้ลแอนด์ ไวร์ จำกัด | E16: ลวดกลมอาบน้ำยา ขนาด 1.20 มม. | F16: 700.27 | G16: KG | H16: 348 | I16: =H16*F16 -> 243693.96 | J16: 334 | K16: =H16-J16 -> 14 | L16: =K16*F16 -> 9803.78 | M16: =K16/H16 -> 0.040229885 | N16: Negotiate | O16: Pawina
A17: 2023 | B17: JAN | C17: PO-23000014 | D17: บริษัท ตงเฉินอีเล็คทริคเคเบิ้ลแอนด์ ไวร์ จำกัด | E17: ลวดกลมอาบน้ำยา ขนาด 0.90 มม. | F17: 256.35 | G17: KG | H17: 349 | I17: =H17*F17 -> 89466.15 | J17: 338.5 | K17: =H17-J17 -> 10.5 | L17: =K17*F17 -> 2691.675 | M17: =K17/H17 -> 0.03008596 | N17: Negotiate | O17: Pawina
A18: 2023 | B18: JAN | C18: PO-23000014 | D18: บริษัท ตงเฉินอีเล็คทริคเคเบิ้ลแอนด์ ไวร์ จำกัด | E18: ลวดกลมอาบน้ำยา ขนาด 1.10 มม. | F18: 101.18 | G18: KG | H18: 348 | I18: =H18*F18 -> 35210.64 | J18: 337 | K18: =H18-J18 -> 11 | L18: =K18*F18 -> 1112.98 | M18: =K18/H18 -> 0.031609195 | N18: Negotiate | O18: Pawina
A19: 2023 | B19: JAN | C19: PO-23000014 | D19: บริษัท ตงเฉินอีเล็คทริคเคเบิ้ลแอนด์ ไวร์ จำกัด | E19: ลวดกลมอาบน้ำยา ขนาด 1.10 มม. | F19: 370.41 | G19: KG | H19: 348 | I19: =H19*F19 -> 128902.68 | J19: 337 | K19: =H19-J19 -> 11 | L19: =K19*F19 -> 4074.51 | M19: =K19/H19 -> 0.031609195 | N19: Negotiate | O19: Pawina
... A62: 2023 | B62: JAN | C62: PO-23000265 | D62: บริษัท ไทยพัฒนสิน (จิ้นเส็ง 2000) จำกัด | E62: ปืนเป่าลมUnior#1508Aขนาด4นิ้วยาว260มิล (เทสรั่ว ของคมกริช) | F62: 6 | G62: EA | H62: 250 | I62: =H62*F62 -> 1500 | J62: 185 | K62: =H62-J62 -> 65 | L62: =K62*F62 -> 390 | M62: =K62/H62 -> 0.26 | N62: Compare + Negotiate | O62: Saniya
A63: 2023 | B63: JAN | C63: PO-23000266 | D63: บริษัท เอทีซี อินดัสตรี (ประเทศไทย)จำกัด | E63: ฝาครอบป้องกันเลื่อยวงเดือน 10-12 นิ้ว พร้อมขายึด | F63: 1 | H63: 3500 | I63: =H63*F63 -> 3500 | J63: 750 | K63: =H63-J63 -> 2750 | L63: =K63*F63 -> 2750 | M63: =K63/H63 -> 0.78571429 | N63: Compare + Negotiate | O63: Saniya
A64: 2023 | B64: JAN | C64: PO-23000282 | D64: ห้างหุ้นส่วนจำกัด บางกอกคอปเปอร์ | E64: ลวดแบนหุ้มกระดาษหนา 0.5 มม. ขนาด 1.4*8.5 มม. | F64: 1053 | G64: KG | H64: 360 | I64: =H64*F64 -> 379080 | J64: 359.5 | K64: =H64-J64 -> 0.5 | L64: =K64*F64 -> 526.5 | M64: =K64/H64 -> 0.0013888889 | N64: Negotiate | O64: Tanida
A65: 2023 | B65: JAN | C65: PO-23000282 | D65: ห้างหุ้นส่วนจำกัด บางกอกคอปเปอร์ | E65: ลวดแบนหุ้มกระดาษหนา 0.5 มม. ขนาด 1.4*8.5 มม. | F65: 1053 | G65: KG | H65: 360 | I65: =H65*F65 -> 379080 | J65: 359.5 | K65: =H65-J65 -> 0.5 | L65: =K65*F65 -> 526.5 | M65: =K65/H65 -> 0.0013888889 | N65: Negotiate | O65: Tanida
A66: 2023 | B66: JAN | C66: PO-23000333 | D66: บริษัท สกิลทูลแอนด์เซอร์วิส จำกัด | E66: เหล็กดูดแรงสูง นีโอไดเมียม D2503 : 25mm. x 3mm. | F66: 20 | G66: EA | H66: 48 | I66: =H66*F66 -> 960 | J66: 45 | K66: =H66-J66 -> 3 | L66: =K66*F66 -> 60 | M66: =K66/H66 -> 0.0625 | N66: Compare + Negotiate | O66: Tanida
A67: 2023 | B67: JAN | C67: PO-23000298 | D67: บริษัท สกิลทูลแอนด์เซอร์วิส จำกัด | E67: เครื่องเจียร์ BOSCH รุ่น GWS900-100S | F67: 1 | G67: EA | H67: 2800 | I67: =H67*F67 -> 2800 | J67: 2500 | K67: =H67-J67 -> 300 | L67: =K67*F67 -> 300 | M67: =K67/H67 -> 0.10714286 | N67: Compare + Negotiate | O67: Saniya
A68: 2023 | B68: JAN | C68: PO-23000298 | D68: บริษัท สกิลทูลแอนด์เซอร์วิส จำกัด | E68: สว่านโรตารี่ 3 ระบบ GBH 2-26 DFR BOSCH | F68: 1 | G68: EA | H68: 7000 | I68: =H68*F68 -> 7000 | J68: 6500 | K68: =H68-J68 -> 500 | L68: =K68*F68 -> 500 | M68: =K68/H68 -> 0.071428571 | N68: Compare + Negotiate | O68: Saniya
A69: 2023 | B69: JAN | C69: PO-23000298 | D69: บริษัท สกิลทูลแอนด์เซอร์วิส จำกัด | E69: เครื่องแว็คคั่ม ยี่ห้อ VALUE รุ่น VE225N | F69: 1 | G69: EA | H69: 4990 | I69: =H69*F69 -> 4990 | J69: 4500 | K69: =H69-J69 -> 490 | L69: =K69*F69 -> 490 | M69: =K69/H69 -> 0.098196393 | N69: Compare + Negotiate | O69: Saniya
A70: 2023 | B70: JAN | C70: PO-23000298 | D70: บริษัท สกิลทูลแอนด์เซอร์วิส จำกัด | E70: สว่านโรตารี่ไร้สายระบบ SDS plus GBH 180-LI | F70: 1 | G70: EA | H70: 10900 | I70: =H70*F70 -> 10900 | J70: 9600 | K70: =H70-J70 -> 1300 | L70: =K70*F70 -> 1300 | M70: =K70/H70 -> 0.11926606 | N70: Compare + Negotiate | O70: Saniya
A71: 2023 | B71: JAN | C71: PO-23000299 | D71: บริษัท แสงชัยมิเตอร์ จำกัด | E71: เครื่องทดสอบความต้านทานดิน KYORITSU 4105A-H | F71: 1 | G71: EA | H71: 13000 | I71: =H71*F71 -> 13000 | J71: 10240 | K71: =H71-J71 -> 2760 | L71: =K71*F71 -> 2760 | M71: =K71/H71 -> 0.21230769 | N71: Compare + Negotiate | O71: Saniya
A72: 2023 | B72: JAN | C72: PO-23000334 | D72: บริษัท แคเรีย เทคโนโลยี (ประเทศไทย) จำกัด | E72: Transfomer Oil Gas Analyzer " Agilent " Model: 8890 | F72: 1 | G72: set | H72: 4076000 | I72: =H72*F72 -> 4076000 | J72: 4000000 | K72: =H72-J72 -> 76000 | L72: =K72*F72 -> 76000 | M72: =K72/H72 -> 0.018645731 | N72: Negotiate | O72: Saniya
A73: 2023 | B73: JAN | C73: PO-23000335 | D73: บริษัท เอทีซี อินดัสตรี (ประเทศไทย)จำกัด | E73: ปืนเป่าลมร้อน HEATGUN BOSCH รุ่นGHG 20-63 2000W. | F73: 1 | G73: EA | H73: 4029 | I73: =H73*F73 -> 4029 | J73: 3850 | K73: =H73-J73 -> 179 | L73: =K73*F73 -> 179 | M73: =K73/H73 -> 0.044427898 | N73: Compare + Negotiate | O73: Saniya
A74: 2023 | B74: JAN | C74: PO-23000336 | D74: บริษัท เอ็นทีดับเบิ้ลยู เอ็นจิเนียริ่ง ซัพพลาย จำกัด | E74: สีสเปรย์ KOBE สีดำด้าน เบอร์ 912 | F74: 36 | G74: EA | H74: 44.5 | I74: =H74*F74 -> 1602 | J74: 39 | K74: =H74-J74 -> 5.5 | L74: =K74*F74 -> 198 | M74: =K74/H74 -> 0.12359551 | N74: Compare + Negotiate | O74: Saniya
A75: 2023 | B75: JAN | C75: PO-23000285 | D75: Wuhu Zhongyuan Import and Export Co.,Ltd | E75: Copper Foil ขนาด 0.40*340 มม. | F75: 1460 | G75: KG | H75: 33.165 | I75: =H75*F75 -> 48420.9 | J75: 32.505 | K75: =H75-J75 -> 0.66 | L75: =K75*F75 -> 963.6 | M75: =K75/H75 -> 0.019900498 | N75: Negotiate | O75: Tanida
... A112: 2023 | B112: FEB | C112: PO-23000401 | D112: บริษัท สกิลทูลแอนด์เซอร์วิส จำกัด | E112: ไม้บรรทัด 2 เมตร 78นิ้ว ฟุตเหล็กสแตนเลส ENDO KEIKI | F112: 1 | G112: EA | H112: 3300 | I112: =H112*F112 -> 3300 | J112: 3000 | K112: =H112-J112 -> 300 | L112: =K112*F112 -> 300 | M112: =K112/H112 -> 0.090909091 | N112: Negotiate | O112: Tanida
A113: 2023 | B113: FEB | C113: PO-23000381,PO-23000453 | D113: บริษัท เอคเม อินซูเลชั่น จำกัด | E113: Wheel Dia.200 mm. thick type/2holes | F113: 124 | G113: EA | H113: 3545 | I113: =H113*F113 -> 439580 | J113: 3365 | K113: =H113-J113 -> 180 | L113: =K113*F113 -> 22320 | M113: =K113/H113 -> 0.05077574 | N113: Negotiate
A114: 2023 | B114: FEB | C114: PO-23000485 | D114: บริษัท ศูนย์บริการเหล็กสยาม จำกัด (มหาชน) | E114: Cold Rolled Steel Sheet (SPCC-SD) ขนาด 1.5*900 มม. | F114: 3000 | G114: kg. | H114: 35 | I114: =H114*F114 -> 105000 | J114: 34.7 | K114: =H114-J114 -> 0.3 | L114: =K114*F114 -> 900 | M114: =K114/H114 -> 0.0085714286 | N114: Compare + Negotiate | O114: Pawina
A115: 2023 | B115: FEB | C115: PO-23000455 | D115: บริษัท ศูนย์บริการเหล็กสยาม จำกัด (มหาชน) | E115: Cold Rolled Steel Sheet (SPCC-SD) ขนาด 1.5*1200 มม. | F115: 6000 | G115: kg. | H115: 35 | I115: =H115*F115 -> 210000 | J115: 34.5 | K115: =H115-J115 -> 0.5 | L115: =K115*F115 -> 3000 | M115: =K115/H115 -> 0.014285714 | N115: Compare + Negotiate | O115: Pawina
A116: 2023 | B116: FEB | C116: PO-23000519 | D116: บริษัท ศูนย์บริการเหล็กสยาม จำกัด (มหาชน) | E116: Cold Rolled Steel Sheet (SPCC-SD) ขนาด 1.5*1200 มม. | F116: 6000 | G116: kg. | H116: 35 | I116: =H116*F116 -> 210000 | J116: 34.5 | K116: =H116-J116 -> 0.5 | L116: =K116*F116 -> 3000 | M116: =K116/H116 -> 0.014285714 | N116: Compare + Negotiate | O116: Pawina
A117: 2023 | B117: FEB | C117: PO-23000431 | D117: บริษัท ไทย ซูปาโก้ เอ็นจิเนียริ่ง แอนด์ ซัพพลาย จำกัด | E117: HARRIS ชุด ตัด Model : 625F LPG | F117: 1 | G117: Set | H117: 5990 | I117: =H117*F117 -> 5990 | J117: 5172.75 | K117: =H117-J117 -> 817.25 | L117: =K117*F117 -> 817.25 | M117: =K117/H117 -> 0.13643573 | N117: Compare + Negotiate | O117: Saniya
A118: 2023 | B118: FEB | C118: PO-23000431 | D118: บริษัท ไทย ซูปาโก้ เอ็นจิเนียริ่ง แอนด์ ซัพพลาย จำกัด | E118: HARRIS เกร์ลม Model : 801DB-10-Oxygen | F118: 1 | G118: set | H118: 2725 | I118: =H118*F118 -> 2725 | J118: 2523.66 | K118: =H118-J118 -> 201.34 | L118: =K118*F118 -> 201.34 | M118: =K118/H118 -> 0.073886239 | N118: Compare + Negotiate | O118: Saniya
A119: 2023 | B119: FEB | C119: PO-23000431 | D119: บริษัท ไทย ซูปาโก้ เอ็นจิเนียริ่ง แอนด์ ซัพพลาย จำกัด | E119: LONGWELL เกย์ CO2 พร้อมฮีตเตอร์ CR-220V | F119: 1 | G119: Set | H119: 2800 | I119: =H119*F119 -> 2800 | J119: 1567.5 | K119: =H119-J119 -> 1232.5 | L119: =K119*F119 -> 1232.5 | M119: =K119/H119 -> 0.44017857 | N119: Compare + Negotiate | O119: Saniya
A120: 2023 | B120: FEB | C120: PO-23000432 | D120: บริษัท ไทยพัฒนสิน (จิ้นเส็ง 2000) จำกัด | E120: คีมปากจิ้งจก ยี่ห้อTajima รุ่น SHP-C8/CN ขนาด 200 มม. | F120: 2 | G120: EA | H120: 412 | I120: =H120*F120 -> 824 | J120: 260 | K120: =H120-J120 -> 152 | L120: =K120*F120 -> 304 | M120: =K120/H120 -> 0.36893204 | N120: Compare + Negotiate | O120: Saniya
A121: 2023 | B121: FEB | C121: PO-23000432 | D121: บริษัท ไทยพัฒนสิน (จิ้นเส็ง 2000) จำกัด | E121: ประแจแหวนนข้างปากตาย เบอร์ 13 ยี่ห้อ KTC | F121: 2 | G121: EA | H121: 1393 | I121: =H121*F121 -> 2786 | J121: 430 | K121: =H121-J121 -> 963 | L121: =K121*F121 -> 1926 | M121: =K121/H121 -> 0.69131371 | N121: Compare + Negotiate | O121: Saniya
A122: 2023 | B122: FEB | C122: PO-23000432 | D122: บริษัท ไทยพัฒนสิน (จิ้นเส็ง 2000) จำกัด | E122: ประแจแหวนนข้างปากตาย เบอร์ 15 ยี่ห้อ KTC | F122: 2 | G122: EA | H122: 1585 | I122: =H122*F122 -> 3170 | J122: 460 | K122: =H122-J122 -> 1125 | L122: =K122*F122 -> 2250 | M122: =K122/H122 -> 0.70977918 | N122: Compare + Negotiate | O122: Saniya
A123: 2023 | B123: FEB | C123: PO-23000432 | D123: บริษัท ไทยพัฒนสิน (จิ้นเส็ง 2000) จำกัด | E123: ประแจแหวนนข้างปากตาย เบอร์ 17 ยี่ห้อ KTC | F123: 2 | G123: EA | H123: 1665 | I123: =H123*F123 -> 3330 | J123: 520 | K123: =H123-J123 -> 1145 | L123: =K123*F123 -> 2290 | M123: =K123/H123 -> 0.68768769 | N123: Compare + Negotiate | O123: Saniya
A124: 2023 | B124: FEB | C124: PO-23000432 | D124: บริษัท ไทยพัฒนสิน (จิ้นเส็ง 2000) จำกัด | E124: ค้อนหัวกลม ยี่ห้อTONE รุ่น BH-10 ขนาด 1 Pound | F124: 2 | G124: EA | H124: 906 | I124: =H124*F124 -> 1812 | J124: 815 | K124: =H124-J124 -> 91 | L124: =K124*F124 -> 182 | M124: =K124/H124 -> 0.1004415 | N124: Compare + Negotiate | O124: Saniya
A125: 2023 | B125: FEB | C125: PO-23000438 | D125: บริษัท เจนบรรเจิด จำกัด | E125: โต๊ะยกปรับระดับ Manual Lift table (รับน้ำหนัก150kg) | F125: 1 | G125: EA | H125: 10700 | I125: =H125*F125 -> 10700 | J125: 9095 | K125: =H125-J125 -> 1605 | L125: =K125*F125 -> 1605 | M125: =K125/H125 -> 0.15 | N125: Compare + Negotiate | O125: Saniya
... A454: 2023 | B454: JUN | C454: PO-23002131 | D454: CORE STEEL CO.,LTD. (Japan) | E454: Silicon Steel Master Coil 023CLF080 | F454: 20000 | G454: kg | H454: 118.25 | I454: =H454*F454 -> 2365000 | J454: 115.5 | K454: =H454-J454 -> 2.75 | L454: =K454*F454 -> 55000 | M454: =K454/H454 -> 0.023255814 | N454: Compare + Negotiate | O454: Pawina
A455: 2023 | B455: JUN | C455: PO-23001795 | D455: REINHAUSEN ITALIA SRL | E455: Tap Changer (Voltage) 3Ph 24kV-150A-L130 ขึ้นกลาง 5P MR | F455: 20 | G455: SET | H455: 6619.98 | I455: =H455*F455 -> 132399.6 | J455: =123.61*38 -> 4697.18 | K455: =H455-J455 -> 1922.8 | L455: =K455*F455 -> 38456 | M455: =K455/H455 -> 0.29045405 | N455: Negotiate | O455: Tanida
A456: 2023 | B456: JUN | C456: PO-23001795 | D456: REINHAUSEN ITALIA SRL | E456: Tap Changer (Voltage) 3Ph 24kV-30A-L320 ขึ้นขวา 5P MR | F456: 10 | G456: SET | H456: 2525.48 | I456: =H456*F456 -> 25254.8 | J456: =48.82*38 -> 1855.16 | K456: =H456-J456 -> 670.32 | L456: =K456*F456 -> 6703.2 | M456: =K456/H456 -> 0.26542281 | N456: Negotiate | O456: Tanida
A457: 2023 | B457: JUN | C457: PO-23001795 | D457: REINHAUSEN ITALIA SRL | E457: Tap Changer (Voltage) 3Ph 36kV-30A-L320 ขึ้นขวา 5P MR | F457: 15 | G457: SET | H457: 2729.16 | I457: =H457*F457 -> 40937.4 | J457: =56.77*38 -> 2157.26 | K457: =H457-J457 -> 571.9 | L457: =K457*F457 -> 8578.5 | M457: =K457/H457 -> 0.20955166 | N457: Negotiate | O457: Tanida
A458: 2023 | B458: JUN | C458: PO-23001795 | D458: REINHAUSEN ITALIA SRL | E458: Tap Changer (Voltage) 3Ph 36kV-60A-L320 ขึ้นขวา 5P MR | F458: 30 | G458: SET | H458: 2729.16 | I458: =H458*F458 -> 81874.8 | J458: =52.99*38 -> 2013.62 | K458: =H458-J458 -> 715.54 | L458: =K458*F458 -> 21466.2 | M458: =K458/H458 -> 0.26218324 | N458: Negotiate | O458: Tanida
A459: 2023 | B459: JUN | C459: PO-23001795 | D459: REINHAUSEN ITALIA SRL | E459: Tap Changer (Voltage) 3Ph 36kV-150A-L320 ขึ้นขวา 5P MR | F459: 30 | G459: SET | H459: 6691.04 | I459: =H459*F459 -> 200731.2 | J459: =123.23*38 -> 4682.74 | K459: =H459-J459 -> 2008.3 | L459: =K459*F459 -> 60249 | M459: =K459/H459 -> 0.30014766 | N459: Negotiate | O459: Tanida
A460: 2023 | B460: JUN | C460: PO-23001836 | D460: บริษัท ทีม สยาม จำกัด | E460: Partition plate-ATP-UK (UK6N) | F460: 100 | G460: EA | H460: 28.64 | I460: =H460*F460 -> 2864 | J460: 14 | K460: =H460-J460 -> 14.64 | L460: =K460*F460 -> 1464 | M460: =K460/H460 -> 0.51117318 | N460: Compare + Negotiate | O460: Tanida
A461: 2023 | B461: JUN | C461: PO-23001843 | D461: ห้างหุ้นส่วนจำกัด บางกอกคอปเปอร์ | E461: ลวดแบนหุ้มกระดาษหนา 0.5 มม. ขนาด 2.0*6 มม. | F461: 210.8 | G461: KG | H461: 351 | I461: =H461*F461 -> 73990.8 | J461: 350 | K461: =H461-J461 -> 1 | L461: =K461*F461 -> 210.8 | M461: =K461/H461 -> 0.0028490028 | N461: Negotiate | O461: Tanida
A462: 2023 | B462: JUN | C462: PO-23001872 | D462: บริษัท วินเนอร์ นัมเบอร์เพลท จำกัด | E462: แผ่น Stainless เครื่องหมายการรับรอง PEA PRODUCT ACCEPTANCE+E | F462: 11 | G462: EA | H462: 400 | I462: =H462*F462 -> 4400 | J462: 385 | K462: =H462-J462 -> 15 | L462: =K462*F462 -> 165 | M462: =K462/H462 -> 0.0375 | N462: Compare + Negotiate | O462: Tanida
A463: 2023 | B463: JUN | C463: PO-23001876 | D463: บริษัท เอสพีซี โกลบอล โลจิสติกส์ จำกัด | E463: Pack & Lashing+Cert.SOF-220015 (ตู้ 40’OT และ ตู้ 20’FR) | F463: 1 | G463: JOB | H463: 52500 | I463: =H463*F463 -> 52500 | J463: 51500 | K463: =H463-J463 -> 1000 | L463: =K463*F463 -> 1000 | M463: =K463/H463 -> 0.019047619 | N463: Compare + Negotiate | O463: Tanida
A464: 2023 | B464: JUN | C464: PO-23001905 | D464: ห้างหุ้นส่วนจำกัด บางกอกคอปเปอร์ | E464: ลวดแบนหุ้มกระดาษหนา 0.5 มม. ขนาด 2.6*6 มม. | F464: 1000 | G464: KG | H464: 351 | I464: =H464*F464 -> 351000 | J464: 350 | K464: =H464-J464 -> 1 | L464: =K464*F464 -> 1000 | M464: =K464/H464 -> 0.0028490028 | N464: Negotiate | O464: Tanida
A465: 2023 | B465: JUN | C465: PO-23001921 | D465: ห้างหุ้นส่วนจำกัด บางกอกคอปเปอร์ | E465: ลวดแบนหุ้มกระดาษหนา 0.5 มม. ขนาด 3.0*5.5 มม. | F465: 616.1 | G465: KG | H465: 351 | I465: =H465*F465 -> 216251.1 | J465: 350 | K465: =H465-J465 -> 1 | L465: =K465*F465 -> 616.1 | M465: =K465/H465 -> 0.0028490028 | N465: Negotiate | O465: Tanida
A466: 2023 | B466: JUN | C466: PO-23001935 | D466: ห้างหุ้นส่วนจำกัด เอ็ม.เอ็น. อีเล็คทริค ซัพพลาย | E466: สายทองแดงเปลือย | F466: 1 | G466: PO | H466: 79500 | I466: =H466*F466 -> 79500 | J466: 77894 | K466: =H466-J466 -> 1606 | L466: =K466*F466 -> 1606 | M466: =K466/H466 -> 0.020201258 | N466: Compare + Negotiate | O466: Tanida
A467: 2023 | B467: JUN | C467: PO-23001950 | D467: บริษัท บ้านไฟฟ้า จำกัด | E467: ข้อตอสายไฟแบบย้ำ-หุ้ม BF 1.5 สีแดง T.LUG | F467: 5 | G467: Pack | H467: 225 | I467: =H467*F467 -> 1125 | J467: 180 | K467: =H467-J467 -> 45 | L467: =K467*F467 -> 225 | M467: =K467/H467 -> 0.2 | N467: Compare + Negotiate | O467: Tanida
A468: 2023 | B468: JUN | C468: PO-23001944 | D468: ห้างหุ้นส่วนจำกัด บางกอกคอปเปอร์ | E468: ลวดแบนหุ้มกระดาษหนา 0.5 มม. ขนาด 2.0*5.0 มม. | F468: 357.4 | G468: KG | H468: 351 | I468: =H468*F468 -> 125447.4 | J468: 350 | K468: =H468-J468 -> 1 | L468: =K468*F468 -> 357.4 | M468: =K468/H468 -> 0.0028490028 | N468: Negotiate | O468: Tanida
A469: 2023 | B469: JUN | C469: PO-23002013 | D469: ห้างหุ้นส่วนจำกัด บางกอกคอปเปอร์ | E469: ลวดแบนหุ้มกระดาษหนา 0.5 มม. และ 0.6 มม. | F469: 6886.4 | G469: KG | H469: 351 | I469: =H469*F469 -> 2417126.4 | J469: 349 | K469: =H469-J469 -> 2 | L469: =K469*F469 -> 13772.8 | M469: =K469/H469 -> 0.0056980057 | N469: Negotiate | O469: Tanida
A470: 2023 | B470: JUN | C470: PO-23002030 | D470: บริษัท แพน เอเซีย แพคกิ้ง จำกัด | E470: Wooden Pallet 1900*1110 MM ฐานไม้สำหรับใส่หม้อแปลง Dry type | F470: 10 | G470: EA | H470: 3450 | I470: =H470*F470 -> 34500 | J470: 3350 | K470: =H470-J470 -> 100 | L470: =K470*F470 -> 1000 | M470: =K470/H470 -> 0.028985507 | N470: Compare + Negotiate | O470: Tanida
A471: 2023 | B471: JUN | C471: PO-23002051 | D471: บริษัท พี ซี อีลีแมค จำกัด | E471: Cover Box for Bushing (W400 * L980 * H350) | F471: 6 | G471: EA | H471: 5000 | I471: =H471*F471 -> 30000 | J471: 4500 | K471: =H471-J471 -> 500 | L471: =K471*F471 -> 3000 | M471: =K471/H471 -> 0.1 | N471: Negotiate | O471: Pawina
... A528: 2023 | B528: JUL | C528: PO-23002485 | D528: บริษัท พรอสเปอร์ อี แอนด์ ที จำกัด | E528: CABLE GLAND Size 50S TYPE A2F | F528: 99 | G528: EA | H528: 1500 | I528: =H528*F528 -> 148500 | J528: 1350 | K528: =H528-J528 -> 150 | L528: =K528*F528 -> 14850 | M528: =K528/H528 -> 0.1 | N528: Negotiate | O528: Tanida
A529: 2023 | B529: AUG | D529: บริษัท พรอสเปอร์ อี แอนด์ ที จำกัด | E529: CABLE GLAND Size 50S TYPE A2F | F529: 160 | G529: EA | H529: 1500 | I529: =H529*F529 -> 240000 | J529: 1350 | K529: =H529-J529 -> 150 | L529: =K529*F529 -> 24000 | M529: =K529/H529 -> 0.1 | N529: Compare + Negotiate | O529: Tanida
A530: 2023 | B530: AUG | C530: PO-23002599 | D530: บริษัท พี.เอส.พี.สเปเชียลตี้ส์ จำกัด (มหาชน) | E530: น้ำมันหม้อแปลง Transform INH | F530: 28000 | G530: ลิตร | H530: 35.5 | I530: =H530*F530 -> 994000 | J530: 35 | K530: =H530-J530 -> 0.5 | L530: =K530*F530 -> 14000 | M530: =K530/H530 -> 0.014084507 | N530: Compare + Negotiate | O530: Pawina
A531: 2023 | B531: AUG | C531: PO-23002507 | D531: บริษัท พี.เอส.พี.สเปเชียลตี้ส์ จำกัด (มหาชน) | E531: น้ำมันหม้อแปลง Transform INH | F531: 56000 | G531: ลิตร | H531: 35.5 | I531: =H531*F531 -> 1988000 | J531: 35 | K531: =H531-J531 -> 0.5 | L531: =K531*F531 -> 28000 | M531: =K531/H531 -> 0.014084507 | N531: Compare + Negotiate | O531: Pawina
A532: 2023 | B532: AUG | C532: PO-23002591 | D532: บริษัท สยาม วิน บอร์น จำกัด | E532: เหล็กแผ่นS400 หนา6.0มม.กว้าง1524มม.ยาว3048มม. | F532: 20 | G532: แผ่น | H532: 5726 | I532: =H532*F532 -> 114520 | J532: 5500 | K532: =H532-J532 -> 226 | L532: =K532*F532 -> 4520 | M532: =K532/H532 -> 0.039469088 | N532: Compare + Negotiate | O532: Pawina
A533: 2023 | B533: AUG | C533: PO-23002591 | D533: บริษัท สยาม วิน บอร์น จำกัด | E533: เหล็กแผ่นS400หนา19.0 มม.กว้าง1219มม.ยาว2438มม. | F533: 1 | G533: แผ่น | H533: 13140 | I533: =H533*F533 -> 13140 | J533: 13000 | K533: =H533-J533 -> 140 | L533: =K533*F533 -> 140 | M533: =K533/H533 -> 0.01065449 | N533: Compare + Negotiate | O533: Pawina
A534: 2023 | B534: AUG | C534: PO-23002448 | D534: บริษัท ไทยสเปเชี่ยลแก๊ส จำกัด | E534: ไนโตรเจน | F534: 2 | G534: ถัง | H534: 240 | I534: =H534*F534 -> 480 | J534: 168 | K534: =H534-J534 -> 72 | L534: =K534*F534 -> 144 | M534: =K534/H534 -> 0.3 | N534: Compare + Negotiate | O534: Saniya
A535: 2023 | B535: AUG | C535: PO-23002501 | D535: บริษัท บิ๊กพาวเวอร์ ซัพพลาย จำกัด | E535: Waterproofing joint Roof metal sheet 2 จุดโรงงาน 5 และ 6 | F535: 1 | G535: job | H535: 160800 | I535: =H535*F535 -> 160800 | J535: 120800 | K535: =H535-J535 -> 40000 | L535: =K535*F535 -> 40000 | M535: =K535/H535 -> 0.24875622 | N535: Negotiate | O535: Saniya
A536: 2023 | B536: AUG | C536: PO-23002529 | D536: บริษัท ไทยสเปเชี่ยลแก๊ส จำกัด | E536: HE UHP 7M3 V.580 (Purity 99.999%) | F536: 10 | G536: ถัง | H536: 9780 | I536: =H536*F536 -> 97800 | J536: 8400 | K536: =H536-J536 -> 1380 | L536: =K536*F536 -> 13800 | M536: =K536/H536 -> 0.14110429 | N536: Compare + Negotiate | O536: Saniya
A537: 2023 | B537: AUG | C537: PO-23002544 | D537: บริษัท เทคโนโลยี อินสตรูเมนท์ จำกัด | E537: TABLI20018 ( Li-ion Blower )เครื่องเป่าลม แบตเตอรี่ ไร้สาย 2 | F537: 1 | G537: EA | H537: 4900 | I537: =H537*F537 -> 4900 | J537: 3750 | K537: =H537-J537 -> 1150 | L537: =K537*F537 -> 1150 | M537: =K537/H537 -> 0.23469388 | N537: Compare + Negotiate | O537: Saniya
A538: 2023 | B538: AUG | C538: PO-23002562 | D538: บริษัท บิ๊กพาวเวอร์ ซัพพลาย จำกัด | E538: Waterproofing joint Roof Sky light =(42x8)=336m. อาคารโรงงาน3 | F538: 1 | G538: job | H538: 70400 | I538: =H538*F538 -> 70400 | J538: 15400 | K538: =H538-J538 -> 55000 | L538: =K538*F538 -> 55000 | M538: =K538/H538 -> 0.78125 | N538: Negotiate | O538: Saniya
A539: 2023 | B539: AUG | C539: PO-23002572 | D539: บริษัท เอทีซี อินดัสตรี (ประเทศไทย)จำกัด | E539: กระเป๋าเครื่องมือช่างProfessional Tools Set120ชิ้นBAK PXTool | F539: 1 | G539: EA | H539: 8990 | I539: =H539*F539 -> 8990 | J539: 8550 | K539: =H539-J539 -> 440 | L539: =K539*F539 -> 440 | M539: =K539/H539 -> 0.04894327 | N539: Compare + Negotiate | O539: Saniya
A540: 2023 | B540: AUG | C540: PO-23002585 | D540: บริษัท ไทยพัฒนสิน (จิ้นเส็ง 2000) จำกัด | E540: OKURA ตลับเก็บสายลมแบบอัตโนมัติ 15 เมตร PU9.5x15.8mm. OK-A15 | F540: 2 | G540: EA | H540: 2500 | I540: =H540*F540 -> 5000 | J540: 2165 | K540: =H540-J540 -> 335 | L540: =K540*F540 -> 670 | M540: =K540/H540 -> 0.134 | N540: Compare + Negotiate | O540: Saniya
A541: 2023 | B541: AUG | C541: PO-23002587 | D541: บริษัท เดลล์ คอร์ปอเรชั่น (ประเทศไทย) จำกัด | E541: แบตเตอรี่ Notebook Dell Latitude 3400 Service Tag F2XKLT2 | F541: 1 | G541: EA | H541: 2800 | I541: =H541*F541 -> 2800 | J541: 1300 | K541: =H541-J541 -> 1500 | L541: =K541*F541 -> 1500 | M541: =K541/H541 -> 0.53571429 | N541: Compare + Negotiate | O541: Saniya
... A737: 2023 | B737: OCT | C737: PO-23003611 | D737: บริษัท ไทยพัฒนสิน (จิ้นเส็ง 2000) จำกัด | E737: ใบเลื่อยสายพานตัดเหล็ก ขนาด M42 27×0.9×5/8 ขนาด 3035mm. | F737: 30 | G737: EA | H737: 820 | I737: =H737*F737 -> 24600 | J737: 675 | K737: =H737-J737 -> 145 | L737: =K737*F737 -> 4350 | M737: =K737/H737 -> 0.17682927 | N737: Compare + Negotiate | O737: Saniya
A738: 2023 | B738: OCT | C738: PO-23003643 | D738: REINHAUSEN SINGAPORE PRIVATE LIMITED | E738: Cedaspe_Radiator Valve Type TW80-B | F738: 100 | G738: EA | H738: =75*39 -> 2925 | I738: =H738*F738 -> 292500 | J738: =68*39 -> 2652 | K738: =H738-J738 -> 273 | L738: =K738*F738 -> 27300 | M738: =K738/H738 -> 0.093333333 | N738: Negotiate | O738: Pawina
A739: 2023 | B739: OCT | C739: PO-23003689 | D739: POSCO International (Thailand) CO., LTD. | E739: Silicon Steel Master Coil 023CLF080 | F739: 100000 | G739: kg | H739: 91 | I739: =H739*F739 -> 9100000 | J739: 90 | K739: =H739-J739 -> 1 | L739: =K739*F739 -> 100000 | M739: =K739/H739 -> 0.010989011 | N739: Negotiate | O739: Pawina
A740: 2023 | B740: OCT | C740: PO-23003682 | D740: บริษัท บางกอกแม็กเน็ตไวร์ จำกัด | E740: ลวดกลมอาบน้ำยา ขนาด 0.65 มม. | F740: 23000 | G740: kg | H740: 344 | I740: =H740*F740 -> 7912000 | J740: 325 | K740: =H740-J740 -> 19 | L740: =K740*F740 -> 437000 | M740: =K740/H740 -> 0.055232558 | N740: Compare + Negotiate | O740: Pawina
A741: 2023 | B741: OCT | C741: PO-23003678 | D741: บริษัท เอคเม อินซูเลชั่น จำกัด | E741: ลูกถ้วยแรงสูง 22kV 20NF250 | F741: 1920 | G741: EA | H741: 325 | I741: =H741*F741 -> 624000 | J741: 310 | K741: =H741-J741 -> 15 | L741: =K741*F741 -> 28800 | M741: =K741/H741 -> 0.046153846 | N741: Negotiate | O741: Pawina
A742: 2023 | B742: OCT | C742: PO-23003678 | D742: บริษัท เอคเม อินซูเลชั่น จำกัด | E742: ลูกถ้วยแรงต่ำ DT1 250 A1 เบอร์1 แกน 12 มม. | F742: 2475 | G742: EA | H742: 26.5 | I742: =H742*F742 -> 65587.5 | J742: 25 | K742: =H742-J742 -> 1.5 | L742: =K742*F742 -> 3712.5 | M742: =K742/H742 -> 0.056603774 | N742: Negotiate | O742: Pawina
A743: 2023 | B743: OCT | C743: PO-23003678 | D743: บริษัท เอคเม อินซูเลชั่น จำกัด | E743: ลูกถ้วยแรงต่ำ DT1 250 B1 เบอร์1 แกน 12 มม. | F743: 2475 | G743: EA | H743: 26.5 | I743: =H743*F743 -> 65587.5 | J743: 25 | K743: =H743-J743 -> 1.5 | L743: =K743*F743 -> 3712.5 | M743: =K743/H743 -> 0.056603774 | N743: Negotiate | O743: Pawina
A744: 2023 | B744: OCT | C744: PO-23003681 | D744: บริษัท เอคเม อินซูเลชั่น จำกัด | E744: กระดาษ Thermopox ขนาด 0.130*105 มม. | F744: 200 | G744: KG | H744: 149 | I744: =H744*F744 -> 29800 | J744: 148 | K744: =H744-J744 -> 1 | L744: =K744*F744 -> 200 | M744: =K744/H744 -> 0.0067114094 | N744: Negotiate | O744: Pawina
A745: 2023 | B745: OCT | C745: PO-23003681 | D745: บริษัท เอคเม อินซูเลชั่น จำกัด | E745: กระดาษ Thermopox ขนาด 0.130*105 มม. | F745: 100 | G745: KG | H745: 149 | I745: =H745*F745 -> 14900 | J745: 148 | K745: =H745-J745 -> 1 | L745: =K745*F745 -> 100 | M745: =K745/H745 -> 0.0067114094 | N745: Negotiate | O745: Pawina
A746: 2023 | B746: OCT | C746: PO-23003681 | D746: บริษัท เอคเม อินซูเลชั่น จำกัด | E746: กระดาษ Thermopox ขนาด 0.130*211มม. | F746: 400 | G746: KG | H746: 149 | I746: =H746*F746 -> 59600 | J746: 148 | K746: =H746-J746 -> 1 | L746: =K746*F746 -> 400 | M746: =K746/H746 -> 0.0067114094 | N746: Negotiate | O746: Pawina
A747: 2023 | B747: OCT | C747: PO-23003681 | D747: บริษัท เอคเม อินซูเลชั่น จำกัด | E747: กระดาษ Thermopox ขนาด 0.130*211มม. | F747: 450 | G747: KG | H747: 149 | I747: =H747*F747 -> 67050 | J747: 148 | K747: =H747-J747 -> 1 | L747: =K747*F747 -> 450 | M747: =K747/H747 -> 0.0067114094 | N747: Negotiate | O747: Pawina
A748: 2023 | B748: OCT | C748: PO-23003681 | D748: บริษัท เอคเม อินซูเลชั่น จำกัด | E748: กระดาษ Thermopox ขนาด 0.130*315 มม. | F748: 400 | G748: KG | H748: 149 | I748: =H748*F748 -> 59600 | J748: 148 | K748: =H748-J748 -> 1 | L748: =K748*F748 -> 400 | M748: =K748/H748 -> 0.0067114094 | N748: Negotiate | O748: Pawina
A749: 2023 | B749: OCT | C749: PO-23003681 | D749: บริษัท เอคเม อินซูเลชั่น จำกัด | E749: กระดาษ Thermopox ขนาด 0.130*315 มม. | F749: 400 | G749: KG | H749: 149 | I749: =H749*F749 -> 59600 | J749: 148 | K749: =H749-J749 -> 1 | L749: =K749*F749 -> 400 | M749: =K749/H749 -> 0.0067114094 | N749: Negotiate | O749: Pawina
A750: 2023 | B750: OCT | C750: PO-23003681 | D750: บริษัท เอคเม อินซูเลชั่น จำกัด | E750: กระดาษ Thermopox ขนาด 0.130*315 มม. | F750: 100 | G750: KG | H750: 149 | I750: =H750*F750 -> 14900 | J750: 148 | K750: =H750-J750 -> 1 | L750: =K750*F750 -> 100 | M750: =K750/H750 -> 0.0067114094 | N750: Negotiate | O750: Pawina
... A814: 2023 | B814: OCT | C814: PO-23003617 | D814: บริษัท ยูไนเต็ดคอปเปอร์ จำกัด | E814: ทองแดงเส้นแบนขนาด 10x200mm. | F814: 1 | G814: SET | H814: 189652 | I814: =H814*F814 -> 189652 | J814: 186816 | K814: =H814-J814 -> 2836 | L814: =K814*F814 -> 2836 | M814: =K814/H814 -> 0.014953705 | N814: Negotiate | O814: Tanida
A815: 2023 | B815: OCT | C815: PO-23003630 | D815: บริษัท บางกอกแม็กเน็ตไวร์ จำกัด | E815: ลวดกลมอาบน้ำยา ขนาด 2.90 มม. | F815: 346.45 | G815: KG | H815: =J815+0.23 -> 363.41 | I815: =H815*F815 -> 125903.39 | J815: 363.18 | K815: =H815-J815 -> 0.23 | L815: =K815*F815 -> 79.6835 | M815: =K815/H815 -> 0.00063289398 | N815: Negotiate | O815: Tanida
A816: 2023 | B816: OCT | C816: PO-23003629 | D816: บริษัท สหมิตรไวร์ แอนด์ เคเบิ้ล จำกัด | E816: ลวดแบนหุ้มกระดาษหนา 0.5 มม. ขนาด 2.0*6 มม. | F816: 216 | G816: KG | H816: 369 | I816: =H816*F816 -> 79704 | J816: 334 | K816: =H816-J816 -> 35 | L816: =K816*F816 -> 7560 | M816: =K816/H816 -> 0.094850949 | N816: Compare + Negotiate | O816: Tanida
A817: 2023 | B817: OCT | C817: PO-23003642 | D817: บริษัท บางกอกแม็กเน็ตไวร์ จำกัด | E817: ลวดกลมอาบน้ำยา ขนาด 2.60 มม. | F817: 364.42 | G817: KG | H817: =J817+0.23 -> 347.21 | I817: =H817*F817 -> 126530.27 | J817: 346.98 | K817: =H817-J817 -> 0.23 | L817: =K817*F817 -> 83.8166 | M817: =K817/H817 -> 0.00066242332 | N817: Negotiate | O817: Tanida
A818: 2023 | B818: OCT | C818: PO-23003648 | D818: บริษัท สหมิตรไวร์ แอนด์ เคเบิ้ล จำกัด | E818: ลวดแบนหุ้มกระดาษหนา 0.5 มม. | F818: 2258 | G818: KG | H818: 369 | I818: =H818*F818 -> 833202 | J818: 334 | K818: =H818-J818 -> 35 | L818: =K818*F818 -> 79030 | M818: =K818/H818 -> 0.094850949 | N818: Compare + Negotiate | O818: Tanida
A819: 2023 | B819: OCT | C819: PO-23003693 | D819: บริษัท กิ้มเฮงเชียง จำกัด | E819: ทองแดงเส้นแบน | F819: 487.1 | G819: KG | H819: 360 | I819: =H819*F819 -> 175356 | J819: 345 | K819: =H819-J819 -> 15 | L819: =K819*F819 -> 7306.5 | M819: =K819/H819 -> 0.041666667 | N819: Compare + Negotiate | O819: Tanida
A820: 2023 | B820: OCT | C820: PO-23003655 | D820: NINGBO JINTIAN COPPER (GROUP) CO.,LTD | E820: Copper Foil (Fabrication cost) | F820: 10320 | G820: KG | H820: 34.22 | I820: =H820*F820 -> 353150.4 | J820: 34.04 | K820: =H820-J820 -> 0.18 | L820: =K820*F820 -> 1857.6 | M820: =K820/H820 -> 0.0052600818 | N820: Compare + Negotiate | O820: Tanida
A821: 2023 | B821: OCT | C821: PO-23003740 | D821: บริษัท สหมิตรไวร์ แอนด์ เคเบิ้ล จำกัด | E821: ลวดแบนหุ้มกระดาษหนา 0.5 มม. | F821: 2413 | G821: KG | H821: 369 | I821: =H821*F821 -> 890397 | J821: 334 | K821: =H821-J821 -> 35 | L821: =K821*F821 -> 84455 | M821: =K821/H821 -> 0.094850949 | N821: Compare + Negotiate | O821: Tanida
...

Sheet สรุป-รายเดือน
A1: เดือน | B1: 2021 | E1: สรุปผล | F1: COST REDUCTION | J1: สรุปผล | L1: Year | M1: 2026
B2: มูลค่าซื้อ | C2: มูลค่าที่ลดลง | D2: คิดเป็น % | F2: มูลค่าซื้อ | G2: มูลค่าต่อรองได้ | H2: มูลค่าเป้าหมาย 3% | I2: คิดเป็น % | P2: % | Q2: เดือน | R2: เงื่อนไขเดิม | S2: เงื่อนไขใหม่ | T2: ผลต่าง | U2: มูลค่าสั่งซื้อ | V2: ลดต้นทุนทางบัญชี | X2: มูลค่าหลังหักส่วนลดเครดดิต
A3: JAN | B3: 35429481 | C3: 2064228.4 | D3: =IF(B3="","",(C3/B3)*100) -> 5.8263014 | E3: =IF(D3="","",IF(D3>=3,$A$47,$A$48)) -> ได้ตามเป้าหมาย | F3: =มูลค่าซื้อ!D3 -> 1.215226e+08 | G3: =SUMIFS(Data!$L$3:$L$9021,Data!$B$3:$B$9021,'สรุป-รายเดือน'!$A3,Data!$A$3:$A$9021,'สรุป-รายเดือน'!$M$1) -> 8059232.2 | H3: =F3*0.03 -> 3645678.1 | I3: =(G3/F3)*100 -> 6.6318791 | J3: =IF(I3="","",IF(I3>=3,$A$47,$A$48)) -> ได้ตามเป้าหมาย | L3: =G3-H3 -> 4413554.1 | M3: =L3/F3 -> 0.036318791 | V3: อัตราดอกเบี้ย 4.25% ต่อปี
A4: FEB | B4: 46183144 | C4: 490222.25 | D4: =IF(B4="","",(C4/B4)*100) -> 1.0614744 | E4: =IF(D4="","",IF(D4>=3,$A$47,$A$48)) -> ไม่ได้ตามเป้าหมาย | F4: =มูลค่าซื้อ!D4 -> 69378145 | G4: =SUMIFS(Data!$L$3:$L$9021,Data!$B$3:$B$9021,'สรุป-รายเดือน'!$A4,Data!$A$3:$A$9021,'สรุป-รายเดือน'!$M$1) -> 1780587.7 | H4: =F4*0.03 -> 2081344.4 | I4: =(G4/F4)*100 -> 2.5664966 | J4: =IF(I4="","",IF(I4>=3,$A$47,$A$48)) -> ไม่ได้ตามเป้าหมาย | L4: =G4-H4 -> -300756.65 | M4: =L4/H4 -> -0.14450115 | R4: 0 | S4: 15 | T4: =S4-R4 -> 15 | U4: 515000 | V4: =(U4*4.25%)*30/360 -> 1823.9583 | W4: =V4/U4 -> 0.0035416667 | X4: =U4-V4 -> 513176.04
A5: MAR | B5: 54764339 | C5: 1120405.4 | D5: =IF(B5="","",(C5/B5)*100) -> 2.0458667 | E5: =IF(D5="","",IF(D5>=3,$A$47,$A$48)) -> ไม่ได้ตามเป้าหมาย | F5: 1.2676433e+08 | G5: =SUMIFS(Data!$L$3:$L$9021,Data!$B$3:$B$9021,'สรุป-รายเดือน'!$A5,Data!$A$3:$A$9021,'สรุป-รายเดือน'!$M$1) -> 3857396.5 | H5: =F5*0.03 -> 3802930 | I5: =(G5/F5)*100 -> 3.0429668 | J5: =IF(I5="","",IF(I5>=3,$A$47,$A$48)) -> ได้ตามเป้าหมาย | L5: =G5-H5 -> 54466.529 | M5: =L5/H5 -> 0.014322254 | R5: 0 | S5: 30 | T5: =S5-R5 -> 30 | U5: 2595435.5 | V5: =(U5*4.25%)*30/360 -> 9192.1674 | W5: =V5/U5 -> 0.0035416667 | X5: =U5-V5 -> 2586243.3
A6: APR | B6: 32497324 | C6: 356214.95 | D6: =IF(B6="","",(C6/B6)*100) -> 1.0961362 | E6: =IF(D6="","",IF(D6>=3,$A$47,$A$48)) -> ไม่ได้ตามเป้าหมาย | F6: 57832810 | G6: =SUMIFS(Data!$L$3:$L$9021,Data!$B$3:$B$9021,'สรุป-รายเดือน'!$A6,Data!$A$3:$A$9021,'สรุป-รายเดือน'!$M$1) -> 739724.92 | H6: =F6*0.03 -> 1734984.3 | I6: =(G6/F6)*100 -> 1.2790748 | J6: =IF(I6="","",IF(I6>=3,$A$47,$A$48)) -> ไม่ได้ตามเป้าหมาย | L6: =G6-H6 -> -995259.38 | M6: =L6/H6 -> -0.57364172 | R6: 30 | S6: 60 | T6: =S6-R6 -> 30 | U6: 3340000 | V6: =(U6*4.25%)*30/360 -> 11829.167 | W6: =V6/U6 -> 0.0035416667 | X6: =U6-V6 -> 3328170.8
A7: MAY | B7: 43171991 | C7: 1477519.8 | D7: =IF(B7="","",(C7/B7)*100) -> 3.4224036 | E7: =IF(D7="","",IF(D7>=3,$A$47,$A$48)) -> ได้ตามเป้าหมาย | F7: 66134405 | G7: =SUMIFS(Data!$L$3:$L$9021,Data!$B$3:$B$9021,'สรุป-รายเดือน'!$A7,Data!$A$3:$A$9021,'สรุป-รายเดือน'!$M$1) -> 1641950.6 | H7: =F7*0.03 -> 1984032.1 | I7: =(G7/F7)*100 -> 2.482748 | J7: =IF(I7="","",IF(I7>=3,$A$47,$A$48)) -> ไม่ได้ตามเป้าหมาย | L7: =G7-H7 -> -342081.55 | M7: =L7/H7 -> -0.17241734
A8: JUN | B8: 58552221 | C8: 612132.27 | D8: =IF(B8="","",(C8/B8)*100) -> 1.0454467 | E8: =IF(D8="","",IF(D8>=3,$A$47,$A$48)) -> ไม่ได้ตามเป้าหมาย | F8: 92229828 | G8: =SUMIFS(Data!$L$3:$L$9021,Data!$B$3:$B$9021,'สรุป-รายเดือน'!$A8,Data!$A$3:$A$9021,'สรุป-รายเดือน'!$M$1) -> 6009822.5 | H8: =F8*0.03 -> 2766894.8 | I8: =(G8/F8)*100 -> 6.5161376 | J8: =IF(I8="","",IF(I8>=3,$A$47,$A$48)) -> ได้ตามเป้าหมาย | L8: =G8-H8 -> 3242927.6 | M8: =L8/H8 -> 1.1720459
A9: JUL | B9: 63322616 | C9: 266870.85 | D9: =IF(B9="","",(C9/B9)*100) -> 0.42144634 | E9: =IF(D9="","",IF(D9>=3,$A$47,$A$48)) -> ไม่ได้ตามเป้าหมาย | F9: 1.1134741e+08 | G9: =SUMIFS(Data!$L$3:$L$9021,Data!$B$3:$B$9021,'สรุป-รายเดือน'!$A9,Data!$A$3:$A$9021,'สรุป-รายเดือน'!$M$1) -> 4132770.9 | H9: =F9*0.03 -> 3340422.2 | I9: =(G9/F9)*100 -> 3.7116005 | J9: =IF(I9="","",IF(I9>=3,$A$47,$A$48)) -> ได้ตามเป้าหมาย | L9: =G9-H9 -> 792348.68 | M9: =L9/H9 -> 0.23720016
A10: AUG | B10: 67114435 | C10: 846288.4 | D10: =IF(B10="","",(C10/B10)*100) -> 1.2609633 | E10: =IF(D10="","",IF(D10>=3,$A$47,$A$48)) -> ไม่ได้ตามเป้าหมาย | F10: =SUMIFS(มูลค่าซื้อ!$D$15:$D$1012,มูลค่าซื้อ!$C$15:$C$1012,'สรุป-รายเดือน'!$A10,มูลค่าซื้อ!$B$15:$B$1012,'สรุป-รายเดือน'!$M$1) -> 0 | G10: =SUMIFS(Data!$L$3:$L$9021,Data!$B$3:$B$9021,'สรุป-รายเดือน'!$A10,Data!$A$3:$A$9021,'สรุป-รายเดือน'!$M$1) -> -435915.2 | H10: =F10*0.03 -> 0 | I10: =(G10/F10)*100 -> #DIV/0! | J10: =IF(I10="","",IF(I10>=3,$A$47,$A$48)) -> #DIV/0! | L10: =G10-H10 -> -435915.2 | M10: =L10/H10 -> #DIV/0!
A11: SEP | B11: 78087740 | C11: 587687.39 | D11: =IF(B11="","",(C11/B11)*100) -> 0.75259878 | E11: =IF(D11="","",IF(D11>=3,$A$47,$A$48)) -> ไม่ได้ตามเป้าหมาย | F11: =SUMIFS(มูลค่าซื้อ!$D$15:$D$1012,มูลค่าซื้อ!$C$15:$C$1012,'สรุป-รายเดือน'!$A11,มูลค่าซื้อ!$B$15:$B$1012,'สรุป-รายเดือน'!$M$1) -> 0 | G11: =SUMIFS(Data!$L$3:$L$9021,Data!$B$3:$B$9021,'สรุป-รายเดือน'!$A11,Data!$A$3:$A$9021,'สรุป-รายเดือน'!$M$1) -> 0 | H11: =F11*0.03 -> 0 | I11: =(G11/F11)*100 -> #DIV/0! | J11: =IF(I11="","",IF(I11>=3,$A$47,$A$48)) -> #DIV/0! | L11: =G11-H11 -> 0 | M11: =L11/H11 -> #DIV/0!
A12: OCT | B12: 51614276 | C12: 729979.18 | D12: =IF(B12="","",(C12/B12)*100) -> 1.414297 | E12: =IF(D12="","",IF(D12>=3,$A$47,$A$48)) -> ไม่ได้ตามเป้าหมาย | F12: =SUMIFS(มูลค่าซื้อ!$D$15:$D$1012,มูลค่าซื้อ!$C$15:$C$1012,'สรุป-รายเดือน'!$A12,มูลค่าซื้อ!$B$15:$B$1012,'สรุป-รายเดือน'!$M$1) -> 0 | G12: =SUMIFS(Data!$L$3:$L$9021,Data!$B$3:$B$9021,'สรุป-รายเดือน'!$A12,Data!$A$3:$A$9021,'สรุป-รายเดือน'!$M$1) -> 0 | H12: =F12*0.03 -> 0 | I12: =(G12/F12)*100 -> #DIV/0! | J12: =IF(I12="","",IF(I12>=3,$A$47,$A$48)) -> #DIV/0! | L12: =G12-H12 -> 0 | M12: =L12/H12 -> #DIV/0!
A13: NOV | B13: 1.5306232e+08 | C13: 976139.6 | D13: =IF(B13="","",(C13/B13)*100) -> 0.63773999 | E13: =IF(D13="","",IF(D13>=3,$A$47,$A$48)) -> ไม่ได้ตามเป้าหมาย | F13: =SUMIFS(มูลค่าซื้อ!$D$15:$D$1012,มูลค่าซื้อ!$C$15:$C$1012,'สรุป-รายเดือน'!$A13,มูลค่าซื้อ!$B$15:$B$1012,'สรุป-รายเดือน'!$M$1) -> 0 | G13: =SUMIFS(Data!$L$3:$L$9021,Data!$B$3:$B$9021,'สรุป-รายเดือน'!$A13,Data!$A$3:$A$9021,'สรุป-รายเดือน'!$M$1) -> 0 | H13: =F13*0.03 -> 0 | I13: =(G13/F13)*100 -> #DIV/0! | J13: =IF(I13="","",IF(I13>=3,$A$47,$A$48)) -> #DIV/0! | L13: =G13-H13 -> 0 | M13: =L13/H13 -> #DIV/0!
A14: DEC | B14: 19994700 | C14: 66880.267 | D14: =IF(B14="","",(C14/B14)*100) -> 0.33448998 | E14: =IF(D14="","",IF(D14>=3,$A$47,$A$48)) -> ไม่ได้ตามเป้าหมาย | F14: =SUMIFS(มูลค่าซื้อ!$D$15:$D$1012,มูลค่าซื้อ!$C$15:$C$1012,'สรุป-รายเดือน'!$A14,มูลค่าซื้อ!$B$15:$B$1012,'สรุป-รายเดือน'!$M$1) -> 0 | G14: =SUMIFS(Data!$L$3:$L$9021,Data!$B$3:$B$9021,'สรุป-รายเดือน'!$A14,Data!$A$3:$A$9021,'สรุป-รายเดือน'!$M$1) -> 0 | H14: =F14*0.03 -> 0 | I14: =(G14/F14)*100 -> #DIV/0! | J14: =IF(I14="","",IF(I14>=3,$A$47,$A$48)) -> #DIV/0! | L14: =G14-H14 -> 0 | M14: =L14/H14 -> #DIV/0!
A15: รวม | B15: =SUM(B3:B14) -> 7.0379458e+08 | C15: =SUM(C3:C14) -> 9594568.7 | D15: =IF(B15="","",(C15/B15)*100) -> 1.3632626 | E15: =IF(D15="","",IF(D15>=3,$A$47,$A$48)) -> ไม่ได้ตามเป้าหมาย | F15: =SUM(F3:F14) -> 6.4520953e+08 | G15: =SUM(G3:G14) -> 25785570 | H15: =SUM(H3:H14) -> 19356286 | I15: =IF(F15="","",(G15/F15)*100) -> 3.9964645 | J15: =IF(I15="","",IF(I15>=3,$A$47,$A$48)) -> ได้ตามเป้าหมาย
A36: รับทราบผลการดำเนินการงาน | G36: คุณปวิณา ใจดี
G37: คุณธนิดา ธรรมสุนทร
G38: คุณยุวนิต โนจันทร์
A47: ได้ตามเป้าหมาย
A48: ไม่ได้ตามเป้าหมาย

Sheet Sheet2
A2: MONTHLY PERFORMANCE
A4: Month | B4: Purchase Value (MB) | C4: Cost Reduction (MB) | D4: % Saving | E4: Status
A5: JAN | B5: 121.5 | C5: 8.06 | D5: 0.0663
A6: FEB | B6: 69.4 | C6: 1.78 | D6: 0.0257
A7: MAR | B7: 126.8 | C7: 3.86 | D7: 0.0304
A8: APR | B8: 57.8 | C8: 0.74 | D8: 0.0128
A9: MAY | B9: 66.1 | C9: 1.64 | D9: 0.0248
A10: JUN | B10: 92.2 | C10: 6.01 | D10: 0.0652
A11: JUL | B11: 111.3 | C11: 4.13 | D11: 0.0371
A12: AUG
A13: SEP
A14: OCT
A15: NOV
A16: Total | B16: =SUM(B5:B15) -> 645.1 | C16: =SUM(C5:C15) -> 26.22 | D16: =C16/B16 -> 0.040644861

Sheet สรุป-รายปี
B2: Year | C2: Purchase Value | D2: Actual Cost saving | E2: % Cost Saving
B3: 2023 | C3: =SUMIF(มูลค่าซื้อ!$B$15:$B$29,'สรุป-รายปี'!$B3,มูลค่าซื้อ!$D$15:$D$1012) -> 0 | D3: =SUMIF(Data!$A$3:$A$9021,'สรุป-รายปี'!$B3,Data!$L$3:$L$9021) -> 12809342 | E3: =D3/C3 -> #DIV/0!
B4: 2024 | C4: =SUMIF(มูลค่าซื้อ!$B$15:$B$29,'สรุป-รายปี'!$B4,มูลค่าซื้อ!$D$15:$D$1012) -> 1.9384578e+08 | D4: =SUMIF(Data!$A$3:$A$9021,'สรุป-รายปี'!$B4,Data!$L$3:$L$9021) -> 19695502 | E4: =D4/C4 -> 0.10160397
B5: 2025 | C5: =SUMIF(มูลค่าซื้อ!$B$15:$B$29,'สรุป-รายปี'!$B5,มูลค่าซื้อ!$D$15:$D$1012) -> 1.5730847e+09 | D5: =SUMIF(Data!$A$3:$A$9021,'สรุป-รายปี'!$B5,Data!$L$3:$L$9021) -> 38838937 | E5: =D5/C5 -> 0.024689667
B6: 2026 | E6: =D6/C6 -> #DIV/0!
B7: 2027 | E7: =D7/C7 -> #DIV/0!
B8: 2028 | E8: =D8/C8 -> #DIV/0!
B9: 2029 | E9: =D9/C9 -> #DIV/0!
B10: 2030 | E10: =D10/C10 -> #DIV/0!

Sheet มูลค่าซื้อ
B2: Year | C2: Month | D2: มูลค่าซื้อ
B3: 2026 | C3: JAN | D3: 1.215226e+08
B4: 2026 | C4: FEB | D4: 69378145
B5: 2026 | C5: MAR | D5: 1.2676433e+08
B6: 2026 | C6: APR | D6: 59523810
B7: 2026 | C7: MAY
B8: 2026 | C8: JUN
B9: 2026 | C9: JUL
B10: 2026 | C10: AUG
B11: 2026 | C11: SEP
B12: 2026 | C12: OCT
B13: 2026 | C13: NOV
B14: 2026 | C14: DEC
B15: 2025 | C15: JAN | D15: 66670985
B16: 2025 | C16: FEB | D16: 90191462
B17: 2025 | C17: MAR | D17: 1.797336e+08
B18: 2025 | C18: APR | D18: 90835578
B19: 2025 | C19: MAY | D19: 1.3899042e+08
B20: 2025 | C20: JUN | D20: 52302145
B21: 2025 | C21: JUL | D21: 2.2804367e+08
B22: 2025 | C22: AUG | D22: 79172245
B23: 2025 | C23: SEP | D23: 86561617
B24: 2025 | C24: OCT | D24: 75043726
B25: 2025 | C25: NOV | D25: 80914511
B26: 2025 | C26: DEC | D26: 4.0462472e+08
... B50: 2023 | C50: DEC | D50: 37586872

Sheet Improve#1
K1: =SUM(K4:K1248) -> 28850082
A3: Month | B3: PO No. | C3: Supplier Name. | D3: Description of Goods/Service | E3: Qty | F3: Unit | G3: ราคาต่ำสุดต่อหน่วย | H3: ราคารวม | I3: ราคาที่ต่อรองได้ | J3: ผลต่าง | K3: รวมที่ต่อรองได้ | L3: % discount | M3: Method for discounts | N3: Person in charge
A4: JAN | B4: PO-25000007 | C4: POSCO International (Thailand) CO., LTD. | D4: Silicon Steel Master Coil 023CLF080 | E4: 80000 | F4: kg. | G4: 75.5 | H4: =G4*E4 -> 6040000 | I4: 75 | J4: =G4-I4 -> 0.5 | K4: =J4*E4 -> 40000 | L4: =J4/G4 -> 0.0066225166 | M4: Compare + Negotiate | N4: Pawina | O4: Compare + Negotiate
A5: JAN | B5: PO-25000012 | C5: บริษัท เอ วี เอ เอ็นจิเนียริ่ง เซอร์วิส จำกัด | D5: แกนแรงสูง ขนาด 12 มม. ผลิตจากกระบวนการ Forging (รูเข้าสายขนา | E5: 500 | F5: EA | G5: 89 | H5: =G5*E5 -> 44500 | I5: 87 | J5: =G5-I5 -> 2 | K5: =J5*E5 -> 1000 | L5: =J5/G5 -> 0.02247191 | M5: Negotiate | N5: Pawina | O5: Avoidance
A6: JAN | B6: PO-25000012 | C6: บริษัท เอ วี เอ เอ็นจิเนียริ่ง เซอร์วิส จำกัด | D6: หางปลาแรงต่ำแบบบาร์ 6 รู แกน 58 มม. | E6: 40 | F6: EA | G6: 4980 | H6: =G6*E6 -> 199200 | I6: 4960 | J6: =G6-I6 -> 20 | K6: =J6*E6 -> 800 | L6: =J6/G6 -> 0.0040160643 | M6: Negotiate | N6: Pawina | O6: เพิ่มเครดิต
A7: JAN | B7: PO-25000012 | C7: บริษัท เอ วี เอ เอ็นจิเนียริ่ง เซอร์วิส จำกัด | D7: คลับทองเหลือง แกนแรงต่ำขนาด 30 มม. เบอร์ 3 (แบบต๊าปเกลียว) | E7: 4 | F7: EA | G7: 475 | H7: =G7*E7 -> 1900 | I7: 465 | J7: =G7-I7 -> 10 | K7: =J7*E7 -> 40 | L7: =J7/G7 -> 0.021052632 | M7: Negotiate | N7: Pawina | O7: Rebate
A8: JAN | B8: PO-25000012 | C8: บริษัท เอ วี เอ เอ็นจิเนียริ่ง เซอร์วิส จำกัด | D8: หางปลาแรงต่ำแบบบาร์ 5 รู แกน 58 มม. ระยะห่าง 80 มม. แถวเดี่ย | E8: 4 | F8: EA | G8: 6850 | H8: =G8*E8 -> 27400 | I8: 6680 | J8: =G8-I8 -> 170 | K8: =J8*E8 -> 680 | L8: =J8/G8 -> 0.024817518 | M8: Negotiate | N8: Pawina | O8: Negotiate
A9: JAN | B9: PO-25000016 | C9: บริษัท สหมิตรไวร์ แอนด์ เคเบิ้ล จำกัด | D9: ลวดแบนหุ้มกระดาษหนา 0.5 มม. | E9: 580 | F9: KG | G9: 378 | H9: =G9*E9 -> 219240 | I9: 348 | J9: =G9-I9 -> 30 | K9: =J9*E9 -> 17400 | L9: =J9/G9 -> 0.079365079 | M9: Compare + Negotiate | N9: Tanida
A10: JAN | B10: PO-25000006 | C10: บริษัท พี ซี อีลีแมค จำกัด | D10: Steel Enclosure ขนาด 2000 x 2600 x 2600 mm. | E10: 8 | F10: set | G10: 129000 | H10: =G10*E10 -> 1032000 | I10: 125000 | J10: =G10-I10 -> 4000 | K10: =J10*E10 -> 32000 | L10: =J10/G10 -> 0.031007752 | M10: Compare + Negotiate | N10: Pawina
A11: JAN | B11: PO-25000034 | C11: บริษัท สยาม วิน บอร์น จำกัด | D11: เหล็กแผ่น SS400 หนา 9.0 มม. กว้าง 1219 มม. ยาว 2438 มม. | E11: 20 | F11: แผ่น | G11: 3195 | H11: =G11*E11 -> 63900 | I11: 3190 | J11: =G11-I11 -> 5 | K11: =J11*E11 -> 100 | L11: =J11/G11 -> 0.0015649452 | M11: Compare + Negotiate | N11: Pawina
A12: JAN | B12: PO-25000034 | C12: บริษัท สยาม วิน บอร์น จำกัด | D12: เหล็กแผ่น SS400 หนา 6.0 มม. กว้าง 1219 มม. ยาว 2438 มม. | E12: 2 | F12: แผ่น | G12: 4730 | H12: =G12*E12 -> 9460 | I12: 4695 | J12: =G12-I12 -> 35 | K12: =J12*E12 -> 70 | L12: =J12/G12 -> 0.0073995772 | M12: Compare + Negotiate | N12: Pawina
A13: JAN | B13: PO-25000036 | C13: ห้างหุ้นส่วนจำกัด เอ็ม.เอ็น. อีเล็คทริค ซัพพลาย | D13: หางปลาต่อสายแบบกลมเปลือย ยี่ห้อ T-LUG CL50-12 | E13: 200 | F13: EA | G13: 15.5 | H13: =G13*E13 -> 3100 | I13: 14.76 | J13: =G13-I13 -> 0.74 | K13: =J13*E13 -> 148 | L13: =J13/G13 -> 0.047741935 | M13: Compare + Negotiate | N13: Tanida
A14: JAN | B14: PO-25000036 | C14: ห้างหุ้นส่วนจำกัด เอ็ม.เอ็น. อีเล็คทริค ซัพพลาย | D14: YAZAKI สายไฟ CVV 12 x1.5sq.mm. | E14: 50 | F14: Metre | G14: 155 | H14: =G14*E14 -> 7750 | I14: 152 | J14: =G14-I14 -> 3 | K14: =J14*E14 -> 150 | L14: =J14/G14 -> 0.019354839 | M14: Compare + Negotiate | N14: Tanida
A15: JAN | B15: PO-25000038 | C15: บริษัท ศูนย์บริการเหล็กสยาม จำกัด (มหาชน) | D15: Cold Rolled Steel Sheet (SPCC-SD) ขนาด 1.2*500 มม. | E15: 3000 | F15: KG | G15: 30 | H15: =G15*E15 -> 90000 | I15: 28 | J15: =G15-I15 -> 2 | K15: =J15*E15 -> 6000 | L15: =J15/G15 -> 0.066666667 | M15: Compare + Negotiate | N15: Pawina
A16: JAN | B16: PO-25000038 | C16: บริษัท ศูนย์บริการเหล็กสยาม จำกัด (มหาชน) | D16: Cold Rolled Steel Sheet (SPCC-SD) ขนาด 1.2*800 มม. | E16: 3000 | F16: KG | G16: 30 | H16: =G16*E16 -> 90000 | I16: 28 | J16: =G16-I16 -> 2 | K16: =J16*E16 -> 6000 | L16: =J16/G16 -> 0.066666667 | M16: Compare + Negotiate | N16: Pawina
A17: JAN | B17: PO-25000038 | C17: บริษัท ศูนย์บริการเหล็กสยาม จำกัด (มหาชน) | D17: Cold Rolled Steel Sheet (SPCC-SD) ขนาด 1.5*1100 มม. | E17: 3000 | F17: KG | G17: 30 | H17: =G17*E17 -> 90000 | I17: 28 | J17: =G17-I17 -> 2 | K17: =J17*E17 -> 6000 | L17: =J17/G17 -> 0.066666667 | M17: Compare + Negotiate | N17: Pawina
A18: JAN | B18: PO-25000038 | C18: บริษัท ศูนย์บริการเหล็กสยาม จำกัด (มหาชน) | D18: Cold Rolled Steel Sheet (SPCC-SD) ขนาด 1.5*1200 มม. | E18: 6000 | F18: KG | G18: 30 | H18: =G18*E18 -> 180000 | I18: 28 | J18: =G18-I18 -> 2 | K18: =J18*E18 -> 12000 | L18: =J18/G18 -> 0.066666667 | M18: Compare + Negotiate | N18: Pawina
A19: JAN | B19: PO-25000040 | C19: บริษัท ยูไนเต็ดคอปเปอร์ จำกัด | D19: ทองแดงเส้นแบน | E19: 578 | F19: KG | G19: 375 | H19: =G19*E19 -> 216750 | I19: 355 | J19: =G19-I19 -> 20 | K19: =J19*E19 -> 11560 | L19: =J19/G19 -> 0.053333333 | M19: Compare + Negotiate | N19: Tanida
A20: JAN | B20: PO-25000041 | C20: บริษัท เจริญทรัพย์ พาเลท จำกัด | D20: Wooden Crate Tr.16 MVA (Fumigation) | E20: 1 | F20: SET | G20: 7650 | H20: =G20*E20 -> 7650 | I20: 5870 | J20: =G20-I20 -> 1780 | K20: =J20*E20 -> 1780 | L20: =J20/G20 -> 0.23267974 | M20: Compare + Negotiate | N20: Tanida
... A34: JAN | B34: PO-25000140 | C34: บริษัท บางกอกแม็กเน็ตไวร์ จำกัด | D34: ลวดกลมอาบน้ำยา | E34: 17400 | F34: KG | G34: 7 | H34: =G34*E34 -> 121800 | I34: 0 | J34: =G34-I34 -> 7 | K34: =J34*E34 -> 121800 | L34: =J34/G34 -> 1 | M34: Negotiate | N34: Tanida
A35: JAN | C35: บริษัท ทีโอเอ-ชูโกกุ เพ้นท์ จำกัด | D35: Rebate ปี2567 | E35: 1 | F35: JOB | G35: 10124405 | H35: =G35*E35 -> 10124405 | I35: 9820672.8 | J35: =G35-I35 -> 303732.15 | K35: =J35*E35 -> 303732.15 | L35: =J35/G35 -> 0.03 | M35: Rebate | N35: Saniya
A36: JAN | B36: PO-25000019 | C36: บริษัท ทีโอเอ-ชูโกกุ เพ้นท์ จำกัด | D36: สีทับหน้า (PU) RAL 7032 CHUGOKU UNY MARINE 100 (DH) | E36: 200 | F36: ถัง | G36: 4700 | H36: =G36*E36 -> 940000 | I36: 4400 | J36: =G36-I36 -> 300 | K36: =J36*E36 -> 60000 | L36: =J36/G36 -> 0.063829787 | M36: Negotiate | N36: Saniya
A37: JAN | B37: PO-25000021 | C37: บริษัท ไทยสเปเชี่ยลแก๊ส จำกัด | D37: ไนโตรเจน | E37: 5 | F37: ถัง | G37: 240 | H37: =G37*E37 -> 1200 | I37: 168 | J37: =G37-I37 -> 72 | K37: =J37*E37 -> 360 | L37: =J37/G37 -> 0.3 | M37: Compare + Negotiate | N37: Saniya
A38: JAN | B38: PO-25000031 | C38: บริษัท ดีเอสไอ คอร์ปอเรชั่น จำกัด | D38: Scotch 3M Filament Tape 48 มม. x 50 มม. เทปใยแก้ว | E38: 144 | F38: Roll | G38: 405 | H38: =G38*E38 -> 58320 | I38: 385 | J38: =G38-I38 -> 20 | K38: =J38*E38 -> 2880 | L38: =J38/G38 -> 0.049382716 | M38: Avoidance | N38: Saniya
A39: JAN | B39: PO-25000051 | C39: บริษัท เอเทค ลิฟท์ติ้ง ทูลส์ จำกัด | D39: สลิงโพลีฯชนิดกลมมีห่วงหัว-ท้าย รับ นน.10T ยาว 4ม. สีส้ม | E39: 1 | F39: EA | G39: 4230 | H39: =G39*E39 -> 4230 | I39: 2800 | J39: =G39-I39 -> 1430 | K39: =J39*E39 -> 1430 | L39: =J39/G39 -> 0.33806147 | M39: Compare + Negotiate | N39: Saniya
A40: JAN | B40: PO-25000061 | C40: บริษัท ไทยพัฒนสิน (จิ้นเส็ง 2000) จำกัด | D40: POLO ดอกเจาะเหล็กคัตเตอร์คาร์ไบด์ Dia.16x35มม. | E40: 5 | F40: EA | G40: 780 | H40: =G40*E40 -> 3900 | I40: 720 | J40: =G40-I40 -> 60 | K40: =J40*E40 -> 300 | L40: =J40/G40 -> 0.076923077 | M40: Compare + Negotiate | N40: Saniya
A41: JAN | B41: PO-25000061 | C41: บริษัท ไทยพัฒนสิน (จิ้นเส็ง 2000) จำกัด | D41: POLO ดอกเจาะเหล็กคัตเตอร์คาร์ไบด์ Dia.18x35มม. | E41: 4 | F41: EA | G41: 780 | H41: =G41*E41 -> 3120 | I41: 720 | J41: =G41-I41 -> 60 | K41: =J41*E41 -> 240 | L41: =J41/G41 -> 0.076923077 | M41: Compare + Negotiate | N41: Saniya
A42: JAN | B42: PO-25000061 | C42: บริษัท ไทยพัฒนสิน (จิ้นเส็ง 2000) จำกัด | D42: POLO ดอกเจาะเหล็กคัตเตอร์คาร์ไบด์ Dia.22x35มม. | E42: 8 | F42: EA | G42: 780 | H42: =G42*E42 -> 6240 | I42: 720 | J42: =G42-I42 -> 60 | K42: =J42*E42 -> 480 | L42: =J42/G42 -> 0.076923077 | M42: Compare + Negotiate | N42: Saniya
A43: JAN | B43: PO-25000061 | C43: บริษัท ไทยพัฒนสิน (จิ้นเส็ง 2000) จำกัด | D43: POLO ดอกเจาะเหล็กคัตเตอร์คาร์ไบด์ Dia.25x35มม. | E43: 3 | F43: EA | G43: 780 | H43: =G43*E43 -> 2340 | I43: 720 | J43: =G43-I43 -> 60 | K43: =J43*E43 -> 180 | L43: =J43/G43 -> 0.076923077 | M43: Compare + Negotiate | N43: Saniya
A44: JAN | B44: PO-25000061 | C44: บริษัท ไทยพัฒนสิน (จิ้นเส็ง 2000) จำกัด | D44: POLO ดอกเจาะเหล็กคัตเตอร์คาร์ไบด์ Dia.28x35มม. | E44: 3 | F44: EA | G44: 882 | H44: =G44*E44 -> 2646 | I44: 820 | J44: =G44-I44 -> 62 | K44: =J44*E44 -> 186 | L44: =J44/G44 -> 0.070294785 | M44: Compare + Negotiate | N44: Saniya
A45: JAN | B45: PO-25000061 | C45: บริษัท ไทยพัฒนสิน (จิ้นเส็ง 2000) จำกัด | D45: POLO ดอกเจาะเหล็กคัตเตอร์คาร์ไบด์ Dia.30x35มม. | E45: 3 | F45: EA | G45: 882 | H45: =G45*E45 -> 2646 | I45: 820 | J45: =G45-I45 -> 62 | K45: =J45*E45 -> 186 | L45: =J45/G45 -> 0.070294785 | M45: Compare + Negotiate | N45: Saniya
A46: JAN | B46: PO-25000070 | C46: บริษัท เอทีซี อินดัสตรี (ประเทศไทย)จำกัด | D46: สีรองพื้น TOA Red Oxide primer G1024D Size 18.925ลิตร/ถัง | E46: 20 | F46: ถัง | G46: 2150 | H46: =G46*E46 -> 43000 | I46: 2135 | J46: =G46-I46 -> 15 | K46: =J46*E46 -> 300 | L46: =J46/G46 -> 0.0069767442 | M46: Compare + Negotiate | N46: Saniya
A47: JAN | B47: PO-25000070 | C47: บริษัท เอทีซี อินดัสตรี (ประเทศไทย)จำกัด | D47: สก๊อตเทปใส Unitape size 1/2" IN x 72 YDS | E47: 576 | F47: Roll | G47: 32 | H47: =G47*E47 -> 18432 | I47: 25 | J47: =G47-I47 -> 7 | K47: =J47*E47 -> 4032 | L47: =J47/G47 -> 0.21875 | M47: Compare + Negotiate | N47: Saniya
... A85: JAN | B85: PO-25000133 | C85: บริษัท เอเบิล ซัคเซส จำกัด | D85: ZWCAD Standard 2025 Standalone License (CAD 2D) Training ( 5 | E85: 5 | F85: EA | G85: 32900 | H85: =G85*E85 -> 164500 | I85: 30000 | J85: =G85-I85 -> 2900 | K85: =J85*E85 -> 14500 | L85: =J85/G85 -> 0.088145897 | M85: Negotiate | N85: Saniya
A86: JAN | B86: PO-25000134 | C86: บริษัท พี เอ็น เทค จำกัด | D86: EQUIPMENT PRODUCT - MANUAL PUSH STATION (FMM) | E86: 1 | F86: JOB | G86: 343500 | H86: =G86*E86 -> 343500 | J86: =G86-I86 -> 343500 | K86: =J86*E86 -> 343500 | L86: =J86/G86 -> 1 | M86: Negotiate | N86: Saniya
A87: JAN | B87: PO-25000165 | C87: บริษัท เอ วี เอ เอ็นจิเนียริ่ง เซอร์วิส จำกัด | D87: แกนทองแดง 12 มม. เบอร์ 1 | E87: 501 | F87: EA | G87: 147 | H87: =G87*E87 -> 73647 | I87: 136 | J87: =G87-I87 -> 11 | K87: =J87*E87 -> 5511 | L87: =J87/G87 -> 0.074829932 | M87: Negotiate | N87: Pawina
A88: JAN | B88: PO-25000165 | C88: บริษัท เอ วี เอ เอ็นจิเนียริ่ง เซอร์วิส จำกัด | D88: แกนทองแดง 30 มม. เบอร์ 3 | E88: 493 | F88: EA | G88: 1100 | H88: =G88*E88 -> 542300 | I88: 1070 | J88: =G88-I88 -> 30 | K88: =J88*E88 -> 14790 | L88: =J88/G88 -> 0.027272727 | M88: Negotiate | N88: Pawina
A89: JAN | B89: PO-25000165 | C89: บริษัท เอ วี เอ เอ็นจิเนียริ่ง เซอร์วิส จำกัด | D89: แหวนหนา แกน 30 มม. | E89: 473 | F89: EA | G89: 185 | H89: =G89*E89 -> 87505 | I89: 180 | J89: =G89-I89 -> 5 | K89: =J89*E89 -> 2365 | L89: =J89/G89 -> 0.027027027 | M89: Negotiate | N89: Pawina
A90: JAN | B90: PO-25000165 | C90: บริษัท เอ วี เอ เอ็นจิเนียริ่ง เซอร์วิส จำกัด | D90: หางปลาแรงต่ำแบบบาร์ 4 รู แกน 30 มม. (PEA) | E90: 300 | F90: EA | G90: 885 | H90: =G90*E90 -> 265500 | I90: 865 | J90: =G90-I90 -> 20 | K90: =J90*E90 -> 6000 | L90: =J90/G90 -> 0.02259887 | M90: Negotiate | N90: Pawina
A91: JAN | B91: PO-25000170 | C91: บริษัท เอ็น.เอช.เค.สตีล จำกัด | D91: Cold Rolled Steel Sheet (SPCC-SD) | E91: 12000 | F91: KG | G91: 29.8 | H91: =G91*E91 -> 357600 | I91: 28 | J91: =G91-I91 -> 1.8 | K91: =J91*E91 -> 21600 | L91: =J91/G91 -> 0.060402685 | M91: Compare + Negotiate | N91: Pawina
A92: JAN | B92: PO-25000190 | C92: บริษัท เซาท์อีสไทยแลนด์ จำกัด | D92: Insulating Supports แรงสูง36kV “Georg Jordan type CA30N” | E92: 5 | F92: EA | G92: 2800 | H92: =G92*E92 -> 14000 | I92: 2625 | J92: =G92-I92 -> 175 | K92: =J92*E92 -> 875 | L92: =J92/G92 -> 0.0625 | M92: Compare + Negotiate | N92: Tanida
A93: JAN | B93: PO-25000212 | C93: บริษัท เมทสัน เพาเวอร์ (ประเทศไทย) จำกัด | D93: น้ำมัน Synthetic Ester ยี่ห้อ MIDEL 7131 | E93: 3000 | F93: ลิตร | G93: 313 | H93: =G93*E93 -> 939000 | I93: 311 | J93: =G93-I93 -> 2 | K93: =J93*E93 -> 6000 | L93: =J93/G93 -> 0.0063897764 | M93: Negotiate | N93: Tanida
A94: JAN | B94: PO-25000213 | C94: บริษัท สหมิตรไวร์ แอนด์ เคเบิ้ล จำกัด | D94: ลวดแบนหุ้มกระดาษหนา 0.5 มม. | E94: 849 | F94: KG | G94: 378 | H94: =G94*E94 -> 320922 | I94: 348 | J94: =G94-I94 -> 30 | K94: =J94*E94 -> 25470 | L94: =J94/G94 -> 0.079365079 | M94: Compare + Negotiate | N94: Tanida
A95: JAN | B95: PO-25000225 | C95: ห้างหุ้นส่วนจำกัด เอ็ม.เอ็น. อีเล็คทริค ซัพพลาย | D95: หางปลาต่อสายแบบกลมเปลือย ยี่ห้อ T-LUG CL50-12 | E95: 200 | F95: EA | G95: 15.5 | H95: =G95*E95 -> 3100 | I95: 14.76 | J95: =G95-I95 -> 0.74 | K95: =J95*E95 -> 148 | L95: =J95/G95 -> 0.047741935 | M95: Compare + Negotiate | N95: Tanida
A96: JAN | B96: PO-25000229 | C96: บริษัท สหมิตรไวร์ แอนด์ เคเบิ้ล จำกัด | D96: ลวดแบนหุ้มกระดาษหนา 0.5 มม. | E96: 1120 | F96: KG | G96: 378 | H96: =G96*E96 -> 423360 | I96: 348 | J96: =G96-I96 -> 30 | K96: =J96*E96 -> 33600 | L96: =J96/G96 -> 0.079365079 | M96: Compare + Negotiate | N96: Tanida
A97: JAN | B97: PO-25000230 | C97: Wuhu Zhongyuan Import and Export Co.,Ltd | D97: Fabrication cost for Copper foil | E97: 21530 | F97: KG | G97: 29.75 | H97: =G97*E97 -> 640517.5 | I97: 27.13 | J97: =G97-I97 -> 2.62 | K97: =J97*E97 -> 56408.6 | L97: =J97/G97 -> 0.088067227 | M97: Compare + Negotiate | N97: Tanida
A98: JAN | B98: PO-25000227 | C98: บริษัท บางกอกแม็กเน็ตไวร์ จำกัด | D98: ลวดกลมอาบน้ำยา ขนาด 1.50 มม. | E98: 4753 | F98: KG | G98: 5 | H98: =G98*E98 -> 23765 | I98: 0 | J98: =G98-I98 -> 5 | K98: =J98*E98 -> 23765 | L98: =J98/G98 -> 1 | M98: Negotiate | N98: Tanida
... A177: FEB | B177: PO-25000371 | C177: บริษัท บ้านไฟฟ้า จำกัด | D177: Insulation barrier (Lower side) For MCCB NF1600-SEW | E177: 18 | F177: EA | G177: 850 | H177: =G177*E177 -> 15300 | I177: 780 | J177: =G177-I177 -> 70 | K177: =J177*E177 -> 1260 | L177: =J177/G177 -> 0.082352941 | M177: Compare + Negotiate | N177: Tanida
A178: FEB | B178: PO-25000380 | C178: บริษัท บางกอกแม็กเน็ตไวร์ จำกัด | D178: ลวดกลมอาบน้ำยา | E178: 1600 | F178: KG | G178: =I178+7 -> 361.85 | H178: =G178*E178 -> 578960 | I178: 354.85 | J178: =G178-I178 -> 7 | K178: =J178*E178 -> 11200 | L178: =J178/G178 -> 0.019345032 | M178: Negotiate | N178: Tanida
A179: FEB | B179: PO-25000380 | C179: บริษัท บางกอกแม็กเน็ตไวร์ จำกัด | D179: ลวดกลมอาบน้ำยา | E179: 2800 | F179: KG | G179: =I179+7 -> 361.69 | H179: =G179*E179 -> 1012732 | I179: 354.69 | J179: =G179-I179 -> 7 | K179: =J179*E179 -> 19600 | L179: =J179/G179 -> 0.01935359 | M179: Negotiate | N179: Tanida
A180: FEB | B180: PO-25000380 | C180: บริษัท บางกอกแม็กเน็ตไวร์ จำกัด | D180: ลวดกลมอาบน้ำยา | E180: 1200 | F180: KG | G180: =I180+7 -> 368.15 | H180: =G180*E180 -> 441780 | I180: 361.15 | J180: =G180-I180 -> 7 | K180: =J180*E180 -> 8400 | L180: =J180/G180 -> 0.019013989 | M180: Negotiate | N180: Tanida
A181: FEB | B181: PO-25000380 | C181: บริษัท บางกอกแม็กเน็ตไวร์ จำกัด | D181: ลวดกลมอาบน้ำยา | E181: 800 | F181: KG | G181: =I181+7 -> 367.57 | H181: =G181*E181 -> 294056 | I181: 360.57 | J181: =G181-I181 -> 7 | K181: =J181*E181 -> 5600 | L181: =J181/G181 -> 0.019043992 | M181: Negotiate | N181: Tanida
A182: FEB | B182: PO-25000380 | C182: บริษัท บางกอกแม็กเน็ตไวร์ จำกัด | D182: ลวดกลมอาบน้ำยา | E182: 2000 | F182: KG | G182: =I182+7 -> 365.74 | H182: =G182*E182 -> 731480 | I182: 358.74 | J182: =G182-I182 -> 7 | K182: =J182*E182 -> 14000 | L182: =J182/G182 -> 0.019139279 | M182: Negotiate | N182: Tanida
A183: FEB | B183: PO-25000380 | C183: บริษัท บางกอกแม็กเน็ตไวร์ จำกัด | D183: ลวดกลมอาบน้ำยา | E183: 2700 | F183: KG | G183: =I183+7 -> 363.05 | H183: =G183*E183 -> 980235 | I183: 356.05 | J183: =G183-I183 -> 7 | K183: =J183*E183 -> 18900 | L183: =J183/G183 -> 0.019281091 | M183: Negotiate | N183: Tanida
A184: FEB | B184: PO-25000380 | C184: บริษัท บางกอกแม็กเน็ตไวร์ จำกัด | D184: ลวดกลมอาบน้ำยา | E184: 2500 | F184: KG | G184: =I184+7 -> 361.92 | H184: =G184*E184 -> 904800 | I184: 354.92 | J184: =G184-I184 -> 7 | K184: =J184*E184 -> 17500 | L184: =J184/G184 -> 0.019341291 | M184: Negotiate | N184: Tanida
A185: FEB | B185: PO-25000380 | C185: บริษัท บางกอกแม็กเน็ตไวร์ จำกัด | D185: ลวดกลมอาบน้ำยา | E185: 5800 | F185: KG | G185: =I185+7 -> 361.46 | H185: =G185*E185 -> 2096468 | I185: 354.46 | J185: =G185-I185 -> 7 | K185: =J185*E185 -> 40600 | L185: =J185/G185 -> 0.019365905 | M185: Negotiate | N185: Tanida
A186: FEB | B186: PO-25000380 | C186: บริษัท บางกอกแม็กเน็ตไวร์ จำกัด | D186: ลวดกลมอาบน้ำยา | E186: 1200 | F186: KG | G186: =I186+7 -> 360.24 | H186: =G186*E186 -> 432288 | I186: 353.24 | J186: =G186-I186 -> 7 | K186: =J186*E186 -> 8400 | L186: =J186/G186 -> 0.01943149 | M186: Negotiate | N186: Tanida
A187: FEB | B187: PO-25000380 | C187: บริษัท บางกอกแม็กเน็ตไวร์ จำกัด | D187: ลวดกลมอาบน้ำยา | E187: 750 | F187: KG | G187: =I187+7 -> 372.42 | H187: =G187*E187 -> 279315 | I187: 365.42 | J187: =G187-I187 -> 7 | K187: =J187*E187 -> 5250 | L187: =J187/G187 -> 0.018795983 | M187: Negotiate | N187: Tanida
A188: FEB | B188: PO-25000380 | C188: บริษัท บางกอกแม็กเน็ตไวร์ จำกัด | D188: ลวดกลมอาบน้ำยา | E188: 800 | F188: KG | G188: =I188+7 -> 364.19 | H188: =G188*E188 -> 291352 | I188: 357.19 | J188: =G188-I188 -> 7 | K188: =J188*E188 -> 5600 | L188: =J188/G188 -> 0.019220736 | M188: Negotiate | N188: Tanida
A189: FEB | B189: PO-25000380 | C189: บริษัท บางกอกแม็กเน็ตไวร์ จำกัด | D189: ลวดกลมอาบน้ำยา | E189: 800 | F189: KG | G189: =I189+7 -> 361.45 | H189: =G189*E189 -> 289160 | I189: 354.45 | J189: =G189-I189 -> 7 | K189: =J189*E189 -> 5600 | L189: =J189/G189 -> 0.019366441 | M189: Negotiate | N189: Tanida
A190: FEB | B190: PO-25000380 | C190: บริษัท บางกอกแม็กเน็ตไวร์ จำกัด | D190: ลวดกลมอาบน้ำยา | E190: 1300 | F190: KG | G190: =I190+7 -> 361.44 | H190: =G190*E190 -> 469872 | I190: 354.44 | J190: =G190-I190 -> 7 | K190: =J190*E190 -> 9100 | L190: =J190/G190 -> 0.019366977 | M190: Negotiate | N190: Tanida
A191: FEB | B191: PO-25000381 | C191: บริษัท สหมิตรไวร์ แอนด์ เคเบิ้ล จำกัด | D191: ลวดแบนหุ้มกระดาษหนา | E191: 2652 | F191: KG | G191: 382 | H191: =G191*E191 -> 1013064 | I191: 350 | J191: =G191-I191 -> 32 | K191: =J191*E191 -> 84864 | L191: =J191/G191 -> 0.083769634 | M191: Compare + Negotiate | N191: Tanida
A192: FEB | B192: PO-25000396 | C192: บริษัท เอคเม อินซูเลชั่น จำกัด | D192: CT 400/1A Current Transformer Class 5P10 10VA | E192: 1 | F192: EA | G192: 29360 | H192: =G192*E192 -> 29360 | I192: 28480 | J192: =G192-I192 -> 880 | K192: =J192*E192 -> 880 | L192: =J192/G192 -> 0.029972752 | M192: Negotiate | N192: Tanida
A193: FEB | B193: PO-25000422 | C193: บริษัท แอลแอลเอสเอส อิเลคทริเคิล ซัพพลาย จำกัด | D193: Flexible Tin Plated Copper Braid 35 SQ.MM. | E193: 100 | F193: เมตร | G193: 320 | H193: =G193*E193 -> 32000 | I193: 300 | J193: =G193-I193 -> 20 | K193: =J193*E193 -> 2000 | L193: =J193/G193 -> 0.0625 | M193: Avoidance | N193: Pawina
A194: FEB | B194: PO-25000480 | C194: บริษัท เอ วี เอ เอ็นจิเนียริ่ง เซอร์วิส จำกัด | D194: หางปลาแรงต่ำแบบบาร์ 6 รู แกน 48 มม. ระยะห่าง 60 มม. | E194: 4 | F194: EA | G194: 4920 | H194: =G194*E194 -> 19680 | I194: 4620 | J194: =G194-I194 -> 300 | K194: =J194*E194 -> 1200 | L194: =J194/G194 -> 0.06097561 | M194: Negotiate | N194: Pawina
A195: FEB | B195: PO-25000470 | C195: บริษัท ต่อกิจ พัฒนา 2019 จำกัด | D195: Control Box Type 3 | E195: 4 | F195: EA | G195: 4000 | H195: =G195*E195 -> 16000 | I195: 3400 | J195: =G195-I195 -> 600 | K195: =J195*E195 -> 2400 | L195: =J195/G195 -> 0.15 | M195: Negotiate | N195: Pawina
A196: FEB | B196: PO-25000470 | C196: บริษัท ต่อกิจ พัฒนา 2019 จำกัด | D196: CABLE BOX TYPE 1 TR.2500 kVA 3Ph 50 Hz 11000-800V | E196: 4 | F196: SET | G196: 34500 | H196: =G196*E196 -> 138000 | I196: 34000 | J196: =G196-I196 -> 500 | K196: =J196*E196 -> 2000 | L196: =J196/G196 -> 0.014492754 | M196: Negotiate | N196: Pawina
A197: FEB | B197: PO-25000478 | C197: บริษัท ต่อกิจ พัฒนา 2019 จำกัด | D197: Control Box Type 3 | E197: 3 | F197: EA | G197: 4000 | H197: =G197*E197 -> 12000 | I197: 3400 | J197: =G197-I197 -> 600 | K197: =J197*E197 -> 1800 | L197: =J197/G197 -> 0.15 | M197: Negotiate | N197: Pawina
A198: FEB | B198: PO-25000478 | C198: บริษัท ต่อกิจ พัฒนา 2019 จำกัด | D198: CABLE BOX TYPE 1 TR.2500 kVA 3Ph 50 Hz 11000-800V | E198: 3 | F198: SET | G198: 34500 | H198: =G198*E198 -> 103500 | I198: 34000 | J198: =G198-I198 -> 500 | K198: =J198*E198 -> 1500 | L198: =J198/G198 -> 0.014492754 | M198: Negotiate | N198: Pawina
A199: FEB | B199: PO-25000508 | C199: บริษัท พีเอส สตีล โปรเซสซิ่ง เซ็นเตอร์ จำกัด | D199: Cold Rolled Steel Sheet (SPCC-SD) ขนาด 1.2*500 มม. | E199: 3000 | F199: KG. | G199: 28 | H199: =G199*E199 -> 84000 | I199: 27.4 | J199: =G199-I199 -> 0.6 | K199: =J199*E199 -> 1800 | L199: =J199/G199 -> 0.021428571 | M199: Compare + Negotiate | N199: Pawina
A200: FEB | B200: PO-25000508 | C200: บริษัท พีเอส สตีล โปรเซสซิ่ง เซ็นเตอร์ จำกัด | D200: Cold Rolled Steel Sheet (SPCC-SD) ขนาด 1.2*800 มม. | E200: 3000 | F200: KG. | G200: 28 | H200: =G200*E200 -> 84000 | I200: 27.4 | J200: =G200-I200 -> 0.6 | K200: =J200*E200 -> 1800 | L200: =J200/G200 -> 0.021428571 | M200: Compare + Negotiate | N200: Pawina
A201: FEB | B201: PO-25000508 | C201: บริษัท พีเอส สตีล โปรเซสซิ่ง เซ็นเตอร์ จำกัด | D201: Cold Rolled Steel Sheet (SPCC-SD) ขนาด 1.2*800 มม. | E201: 3000 | F201: KG. | G201: 28 | H201: =G201*E201 -> 84000 | I201: 27.4 | J201: =G201-I201 -> 0.6 | K201: =J201*E201 -> 1800 | L201: =J201/G201 -> 0.021428571 | M201: Compare + Negotiate | N201: Pawina
A202: FEB | B202: PO-25000508 | C202: บริษัท พีเอส สตีล โปรเซสซิ่ง เซ็นเตอร์ จำกัด | D202: Cold Rolled Steel Sheet (SPCC-SD) ขนาด 1.2*400 มม. | E202: 3000 | F202: KG. | G202: 28 | H202: =G202*E202 -> 84000 | I202: 27.4 | J202: =G202-I202 -> 0.6 | K202: =J202*E202 -> 1800 | L202: =J202/G202 -> 0.021428571 | M202: Compare + Negotiate | N202: Pawina
... A275: MAR | B275: PO-25000823 | C275: บริษัท เอ็น.เอช.เค.สตีล จำกัด | D275: Cold Rolled Steel Sheet (SPCC-SD) ขนาด 1.5*1100 มม. | E275: 3000 | F275: KG. | G275: 28 | H275: =G275*E275 -> 84000 | I275: 27.5 | J275: =G275-I275 -> 0.5 | K275: =J275*E275 -> 1500 | L275: =J275/G275 -> 0.017857143 | M275: Compare + Negotiate | N275: Pawina
A276: MAR | B276: PO-25000819 | C276: CORE STEEL CO.,LTD. (Japan) | D276: Silicon Steel Master Coil 020CLF070 (20SQGD070) | E276: 20000 | F276: KG. | G276: =(2.59*34)+1 -> 89.06 | H276: =G276*E276 -> 1781200 | I276: =(2.55*34)+1 -> 87.7 | J276: =G276-I276 -> 1.36 | K276: =J276*E276 -> 27200 | L276: =J276/G276 -> 0.015270604 | M276: Compare + Negotiate | N276: Pawina
A277: MAR | B277: PO-25000820 | C277: บริษัท เจเอฟอี โชจิ (ประเทศไทย) จำกัด | D277: Silicon Steel Master Coil 023CLF080 | E277: 200000 | F277: KG. | G277: 80.9 | H277: =G277*E277 -> 16180000 | I277: 74.162 | J277: =G277-I277 -> 6.738 | K277: =J277*E277 -> 1347600 | L277: =J277/G277 -> 0.08328801 | M277: Compare + Negotiate | N277: Pawina
A278: MAR | B278: PO-25000867 | C278: บริษัท พี ซี อีลีแมค จำกัด | D278: Control Box (Lamp + Limit switch) | E278: 11 | F278: EA. | G278: 6000 | H278: =G278*E278 -> 66000 | I278: 5700 | J278: =G278-I278 -> 300 | K278: =J278*E278 -> 3300 | L278: =J278/G278 -> 0.05 | M278: Compare + Negotiate | N278: Pawina
A279: MAR | B279: PO-25000867 | C279: บริษัท พี ซี อีลีแมค จำกัด | D279: CABLE BOX TYPE 1 TR.7700 kVA 3Ph 50Hz 22000-800/800V | E279: 7 | F279: SET. | G279: 48500 | H279: =G279*E279 -> 339500 | I279: 45000 | J279: =G279-I279 -> 3500 | K279: =J279*E279 -> 24500 | L279: =J279/G279 -> 0.072164948 | M279: Compare + Negotiate | N279: Pawina
A280: MAR | B280: PO-25000867 | C280: บริษัท พี ซี อีลีแมค จำกัด | D280: Box ตัวเสียบ ขนาด 1250x500x1100 มม. | E280: 8 | F280: SET. | G280: 18000 | H280: =G280*E280 -> 144000 | I280: 15000 | J280: =G280-I280 -> 3000 | K280: =J280*E280 -> 24000 | L280: =J280/G280 -> 0.16666667 | M280: Compare + Negotiate | N280: Pawina
A281: MAR | B281: PO-25000867 | C281: บริษัท พี ซี อีลีแมค จำกัด | D281: Box ตัวเสียบ ขนาด 1640x450x1100 มม. | E281: 8 | F281: SET. | G281: 22000 | H281: =G281*E281 -> 176000 | I281: 18400 | J281: =G281-I281 -> 3600 | K281: =J281*E281 -> 28800 | L281: =J281/G281 -> 0.16363636 | M281: Compare + Negotiate | N281: Pawina
A282: MAR | B282: PO-25000868 | C282: บริษัท พี ซี อีลีแมค จำกัด | D282: Box ตัวเสียบ ขนาด 1250x500x1100 มม. | E282: 17 | F282: SET. | G282: 18000 | H282: =G282*E282 -> 306000 | I282: 15000 | J282: =G282-I282 -> 3000 | K282: =J282*E282 -> 51000 | L282: =J282/G282 -> 0.16666667 | M282: Compare + Negotiate | N282: Pawina
A283: MAR | B283: PO-25000868 | C283: บริษัท พี ซี อีลีแมค จำกัด | D283: Box ตัวเสียบ ขนาด 1640x450x1100 มม. | E283: 17 | F283: SET. | G283: 22000 | H283: =G283*E283 -> 374000 | I283: 18400 | J283: =G283-I283 -> 3600 | K283: =J283*E283 -> 61200 | L283: =J283/G283 -> 0.16363636 | M283: Compare + Negotiate | N283: Pawina
A284: MAR | B284: PO-25000868 | C284: บริษัท พี ซี อีลีแมค จำกัด | D284: CABLE BOX TYPE 1 TR.7700 kVA 3Ph 50Hz 22000-800/800V | E284: 14 | F284: SET. | G284: 48500 | H284: =G284*E284 -> 679000 | I284: 45000 | J284: =G284-I284 -> 3500 | K284: =J284*E284 -> 49000 | L284: =J284/G284 -> 0.072164948 | M284: Compare + Negotiate | N284: Pawina
A285: MAR | B285: PO-25000868 | C285: บริษัท พี ซี อีลีแมค จำกัด | D285: Control Box (Lamp + Limit switch) | E285: 18 | F285: EA. | G285: 6000 | H285: =G285*E285 -> 108000 | I285: 5700 | J285: =G285-I285 -> 300 | K285: =J285*E285 -> 5400 | L285: =J285/G285 -> 0.05 | M285: Compare + Negotiate | N285: Pawina
A286: MAR | B286: PO-25000859 | C286: บริษัท ต่อกิจ พัฒนา 2019 จำกัด | D286: CABLE BOX TYPE 1 TR.2000 kVA 3Ph 50Hz 22000-400/230V | E286: 2 | F286: SET. | G286: 46500 | H286: =G286*E286 -> 93000 | I286: 45500 | J286: =G286-I286 -> 1000 | K286: =J286*E286 -> 2000 | L286: =J286/G286 -> 0.021505376 | M286: Negotiate | N286: Pawina
A287: MAR | B287: PO-25000872 | C287: บริษัท ต่อกิจ พัฒนา 2019 จำกัด | D287: CABLE BOX TYPE 1 TR.50 kVA 3Ph 50Hz 22000-400/230V | E287: 11 | F287: SET. | G287: 34500 | H287: =G287*E287 -> 379500 | I287: 33500 | J287: =G287-I287 -> 1000 | K287: =J287*E287 -> 11000 | L287: =J287/G287 -> 0.028985507 | M287: Negotiate | N287: Pawina
A288: MAR | B288: PO-25000938 | C288: บริษัท พีเอส สตีล โปรเซสซิ่ง เซ็นเตอร์ จำกัด | D288: Cold Rolled Steel Sheet (SPCC-SD) ขนาด 1.2*800 มม. | E288: 9000 | F288: KG. | G288: 27.4 | H288: =G288*E288 -> 246600 | I288: 27 | J288: =G288-I288 -> 0.4 | K288: =J288*E288 -> 3600 | L288: =J288/G288 -> 0.01459854 | M288: Compare + Negotiate | N288: Pawina
... A301: MAR | B301: PO-25000691 | C301: บริษัท เอคเม อินซูเลชั่น จำกัด | D301: Vertical Oil Level With Contact (ARES) | E301: 14 | F301: EA. | G301: 13258.81 | H301: =G301*E301 -> 185623.34 | I301: 5390 | J301: =G301-I301 -> 7868.81 | K301: =J301*E301 -> 110163.34 | L301: =J301/G301 -> 0.59347785 | M301: Compare + Negotiate | N301: Tanida
A302: MAR | B302: PO-25000745 | C302: บริษัท พรอสเปอร์ อี แอนด์ ที จำกัด | D302: CABLE GLAND Size 32 TYPE A2F | E302: =280*2 -> 560 | F302: EA. | G302: 500 | H302: =G302*E302 -> 280000 | I302: 480 | J302: =G302-I302 -> 20 | K302: =J302*E302 -> 11200 | L302: =J302/G302 -> 0.04 | M302: Negotiate | N302: Tanida
A303: MAR | B303: PO-25000776 | C303: ห้างหุ้นส่วนจำกัด เอ็ม.เอ็น. อีเล็คทริค ซัพพลาย | D303: หางปลาต่อสายแบบกลมเปลือย ยี่ห้อ T-LUG CL70-12 | E303: 200 | F303: EA. | G303: 26 | H303: =G303*E303 -> 5200 | I303: 24.6 | J303: =G303-I303 -> 1.4 | K303: =J303*E303 -> 280 | L303: =J303/G303 -> 0.053846154 | M303: Compare + Negotiate | N303: Tanida
A304: MAR | B304: PO-25000778 | C304: Wuhu Zhongyuan Import and Export Co.,Ltd | D304: Fabrication cost for Copper foil | E304: 18780 | F304: KG. | G304: 30.51 | H304: =G304*E304 -> 572977.8 | I304: 26.28 | J304: =G304-I304 -> 4.23 | K304: =J304*E304 -> 79439.4 | L304: =J304/G304 -> 0.13864307 | M304: Negotiate | N304: Tanida
A305: MAR | B305: PO-25000792 | C305: บริษัท ไทยพัฒนสิน (จิ้นเส็ง 2000) จำกัด | D305: UNIOR ประแจแหวนข้างปากตาย 19mm #120/1-19 | E305: 2 | F305: EA. | G305: 375 | H305: =G305*E305 -> 750 | I305: 347 | J305: =G305-I305 -> 28 | K305: =J305*E305 -> 56 | L305: =J305/G305 -> 0.074666667 | M305: Compare + Negotiate | N305: Tanida
A306: MAR | B306: PO-25000792 | C306: บริษัท ไทยพัฒนสิน (จิ้นเส็ง 2000) จำกัด | D306: UNIOR ประแจแหวนข้างปากตาย 21mm #120/1-21 | E306: 2 | F306: EA. | G306: 420 | H306: =G306*E306 -> 840 | I306: 402 | J306: =G306-I306 -> 18 | K306: =J306*E306 -> 36 | L306: =J306/G306 -> 0.042857143 | M306: Compare + Negotiate | N306: Tanida
A307: MAR | B307: PO-25000792 | C307: บริษัท ไทยพัฒนสิน (จิ้นเส็ง 2000) จำกัด | D307: UNIOR ประแจแหวนข้างปากตาย 24mm #120/1-24 | E307: 2 | F307: EA. | G307: 520 | H307: =G307*E307 -> 1040 | I307: 502 | J307: =G307-I307 -> 18 | K307: =J307*E307 -> 36 | L307: =J307/G307 -> 0.034615385 | M307: Compare + Negotiate | N307: Tanida
A308: MAR | B308: PO-25000792 | C308: บริษัท ไทยพัฒนสิน (จิ้นเส็ง 2000) จำกัด | D308: ค้อนยางลดแรงกระแทก Soft Face Hammers 09E-055 | E308: 1 | F308: EA. | G308: 785 | H308: =G308*E308 -> 785 | I308: 780 | J308: =G308-I308 -> 5 | K308: =J308*E308 -> 5 | L308: =J308/G308 -> 0.0063694268 | M308: Compare + Negotiate | N308: Tanida
A309: MAR | B309: PO-25000812 | C309: ห้างหุ้นส่วนจำกัด เอ็ม.เอ็น. อีเล็คทริค ซัพพลาย | D309: หางปลาต่อสายแบบกลมเปลือย ยี่ห้อ T-LUG CL240-12 | E309: 100 | F309: EA. | G309: 190 | H309: =G309*E309 -> 19000 | I309: 182.25 | J309: =G309-I309 -> 7.75 | K309: =J309*E309 -> 775 | L309: =J309/G309 -> 0.040789474 | M309: Compare + Negotiate | N309: Tanida
A310: MAR | B310: PO-25000830 | C310: บริษัท เอทีซี อินดัสตรี (ประเทศไทย)จำกัด | D310: เครื่องเจียรไร้สาย ไร้แปรงถ่าน 100 MM. 20V Max รุ่น DCG405P2 | E310: 3 | F310: EA. | G310: 8250 | H310: =G310*E310 -> 24750 | I310: 8100 | J310: =G310-I310 -> 150 | K310: =J310*E310 -> 450 | L310: =J310/G310 -> 0.018181818 | M310: Negotiate | N310: Tanida
A311: MAR | B311: PO-25000835 | C311: บริษัท ธนากัญญ คอนสตรัคชั่น เวิร์ค จำกัด | D311: Site expense | E311: 1 | F311: EA. | G311: 11657 | H311: =G311*E311 -> 11657 | I311: 3430 | J311: =G311-I311 -> 8227 | K311: =J311*E311 -> 8227 | L311: =J311/G311 -> 0.7057562 | M311: Negotiate | N311: Tanida
A312: MAR | B312: PO-25000856 | C312: บริษัท เอทีซี อินดัสตรี (ประเทศไทย)จำกัด | D312: ตู้แช่เย็นมินิมาร์ท FRESHER 2 ประตู รุ่น FR-2DM8 ขนาด 27.6 Q | E312: 1 | F312: EA. | G312: 36500 | H312: =G312*E312 -> 36500 | I312: 36300 | J312: =G312-I312 -> 200 | K312: =J312*E312 -> 200 | L312: =J312/G312 -> 0.0054794521 | M312: Negotiate | N312: Tanida
A313: MAR | B313: PO-25000884 | C313: บริษัท แครี่บอย มาร์เก็ตติ้ง จำกัด | D313: ตู้ Car-Service (L 2,400 W 1,830 H 900 mm) Shelf Scheme : รถ | E313: 1 | F313: EA. | G313: 158000 | H313: =G313*E313 -> 158000 | I313: 150000 | J313: =G313-I313 -> 8000 | K313: =J313*E313 -> 8000 | L313: =J313/G313 -> 0.050632911 | M313: Negotiate | N313: Tanida
...

Sheet Sheet4
A3: Sum of รวมที่ต่อรองได้ | B3: Column Labels
A4: Row Labels | B4: Dusit | C4: Pawina | D4: Saniya | E4: Tanida | F4: Yuwanit | G4: Grand Total
A5: Avoidance | C5: 242550 | D5: 6960 | E5: 735860 | G5: 985370
A6: Compare + Negotiate | C6: 8720352.6 | D6: 329680.5 | E6: 6428412.4 | F6: 71303.3 | G6: 15549749
A7: Negotiate | B7: 143426.59 | C7: 2917633.7 | D7: 553322 | E7: 2851246.4 | F7: 293198.51 | G7: 6758827.2
A8: Rebate | D8: 303732.15 | G8: 303732.15
A9: เพิ่มเครดิต | B9: 82234.93 | C9: 70.13 | F9: 3364.58 | G9: 85669.64
A10: Grand Total | B10: 225661.52 | C10: 11880606 | D10: 1193694.7 | E10: 10015519 | F10: 367866.39 | G10: 23683348
A13: กลยุทธ์ด้านจัดซื้อ | B13: รวมมูลค่าที่ต่อรองได้ ปี 2568 (บาท) | H13: สัดส่วน
B14: Dusit | C14: Pawina | D14: Saniya | E14: Tanida | F14: Yuwanit | G14: Grand Total
A15: Avoidance | C15: 242550 | D15: 6960 | E15: 735860 | G15: 985370 | H15: =G15/G$20 -> 0.041606027
A16: Compare + Negotiate | C16: 8720352.6 | D16: 329680.5 | E16: 6428412.4 | F16: 71303.3 | G16: 15549749 | H16: =G16/G$20 -> 0.65656886
A17: Negotiate | B17: 143426.59 | C17: 2917633.7 | D17: 553322 | E17: 2851246.4 | F17: 293198.51 | G17: 6758827.2 | H17: =G17/G$20 -> 0.2853831
A18: Rebate | D18: 303732.15 | G18: 303732.15 | H18: =G18/G$20 -> 0.012824713
A19: เพิ่มเครดิต Extend Credit terms | B19: 82234.93 | C19: 70.13 | F19: 3364.58 | G19: 85669.64 | H19: =G19/G$20 -> 0.0036172943
A20: Grand Total (บาท) | B20: 225661.52 | C20: 11880606 | D20: 1193694.7 | E20: 10015519 | F20: 367866.39 | G20: 23683348 | H20: =SUM(H15:H19) -> 1

Sheet Kaizen Cost saving 
C2: ประหยัดเวลาได้ | D2: 10 | F2: นาที/งาน
C3: จำนวนงาน | D3: 16 | F3: =IF(H3=TRUE,"งาน/วัน","งาน/เดือน") -> งาน/เดือน | H3: FALSE
C5: ค่าแรง | D5: =(19625/21)/8 -> 116.81548 | F5: บาท/ชั่วโมง
C6: ทำงาน | D6: 20 | F6: วัน/เดือน
C7: จำนวน | D7: 1 | F7: เดือน/ปี
C10: คิดเป็นผลประหยัด | D10: =IF(H3=TRUE,"("&D2&"/60) x "&D3&" x "&117&" x "&D6&" x "&D7,"("&D2&"/60) x "&D3&" x "&117&" x "&D7) -> (10/60) x 16 x 117 x 1 | H10: บาท/ปี
D12: =IF(H3=TRUE,(D2/60)*D5*D3*D6*D7,(D2/60)*D5*D3*D7) -> 311.50794 | H12: บาท/ปี
C14: Update ค่าแรงต่อชั่วโมง จาก 98.5 บาท/ชม.เป็น 117 บาท/ชม. เมื่อวันที่ 25/02/65
C15: หมายเหตุ
C16: ราคากระดาษแผ่นละ 0.15 บาท
C17: ค่าแรงพนักงานเฉลี่ยทั้งบริษัทเป็น 117 บาท/ชั่วโมง
C18: วิธีการคิดลดการใช้พลังงานเป็นจำนวนเงิน
C19: กิโลวัตต์-ชั่วโมงต่อปี û หน่วยค่าไฟฟ้า (หน่วยละ 4 บาท) เช่น 173*4=692 บาท
C20: ค่าปริ้นท์สี | D20: 3 | E20: บาทต่อแผ่น
C21: ค่าปริ้นท์ขาวดำ | D21: 0.3 | E21: บาทต่อแผ่น

Sheet Set
B1: Month
B2: JAN | C2: 1
B3: FEB | C3: 2
B4: MAR | C4: 3
B5: APR | C5: 4
B6: MAY | C6: 5
B7: JUN | C7: 6
B8: JUL | C8: 7
B9: AUG | C9: 8
B10: SEP | C10: 9
B11: OCT | C11: 10
B12: NOV | C12: 11
B13: DEC | C13: 12
